{
  "items": [
    {
      "battleTime": "20241215T194536.000Z",
      "event": {
        "id": 15000228,
        "mode": "soloShowdown",
        "map": "Safety Center"
      },
      "battle": {
        "mode": "soloShowdown",
        "type": "ranked",
        "rank": 4,
        "trophyChange": 7,
        "players": [
          {
            "tag": "#2LVL2PJ0VV",
            "name": "IamBukk",
            "brawler": {
              "id": 16000088,
              "name": "BUZZ LIGHTYEAR",
              "power": 11,
              "trophies": 144
            }
          },
          {
            "tag": "#2QQVJ08JGG",
            "name": "adrielpokemon",
            "brawler": {
              "id": 16000086,
              "name": "SHADE",
              "power": 7,
              "trophies": 150
            }
          },
          {
            "tag": "#2LJCPU2Q09",
            "name": "Mario 2.0",
            "brawler": {
              "id": 16000013,
              "name": "POCO",
              "power": 5,
              "trophies": 168
            }
          },
          {
            "tag": "#2GL8YLVPGY",
            "name": "fettuccine",
            "brawler": {
              "id": 16000010,
              "name": "EL PRIMO",
              "power": 5,
              "trophies": 168
            }
          },
          {
            "tag": "#JQUGVJ809",
            "name": "Wells00",
            "brawler": {
              "id": 16000088,
              "name": "BUZZ LIGHTYEAR",
              "power": 11,
              "trophies": 163
            }
          },
          {
            "tag": "#RUP2V88QY",
            "name": "That kid",
            "brawler": {
              "id": 16000072,
              "name": "PEARL",
              "power": 1,
              "trophies": 157
            }
          },
          {
            "tag": "#9UYUU0L02",
            "name": "U R WEIRD\u30b7",
            "brawler": {
              "id": 16000088,
              "name": "BUZZ LIGHTYEAR",
              "power": 11,
              "trophies": 160
            }
          },
          {
            "tag": "#2GQQRLCUGP",
            "name": "dragon king",
            "brawler": {
              "id": 16000010,
              "name": "EL PRIMO",
              "power": 10,
              "trophies": 149
            }
          },
          {
            "tag": "#2QR2CR8PU2",
            "name": "HADES66",
            "brawler": {
              "id": 16000004,
              "name": "RICO",
              "power": 6,
              "trophies": 152
            }
          },
          {
            "tag": "#2Q0GQVJGVV",
            "name": "elmegapro",
            "brawler": {
              "id": 16000088,
              "name": "BUZZ LIGHTYEAR",
              "power": 11,
              "trophies": 162
            }
          }
        ]
      }
    },
    {
      "battleTime": "20241215T194137.000Z",
      "event": {
        "id": 15000228,
        "mode": "soloShowdown",
        "map": "Safety Center"
      },
      "battle": {
        "mode": "soloShowdown",
        "type": "ranked",
        "rank": 3,
        "trophyChange": 7,
        "players": [
          {
            "tag": "#LQVP8LVQ9",
            "name": "Bubba",
            "brawler": {
              "id": 16000088,
              "name": "BUZZ LIGHTYEAR",
              "power": 11,
              "trophies": 159
            }
          },
          {
            "tag": "#2LVPY8UYC",
            "name": "moki demolisher",
            "brawler": {
              "id": 16000038,
              "name": "SURGE",
              "power": 9,
              "trophies": 176
            }
          },
          {
            "tag": "#2GL8YLVPGY",
            "name": "fettuccine",
            "brawler": {
              "id": 16000010,
              "name": "EL PRIMO",
              "power": 5,
              "trophies": 161
            }
          },
          {
            "tag": "#GYV90ULR2",
            "name": "Delgrip03",
            "brawler": {
              "id": 16000037,
              "name": "SPROUT",
              "power": 8,
              "trophies": 179
            }
          },
          {
            "tag": "#RRP8U8L0G",
            "name": "Adam",
            "brawler": {
              "id": 16000000,
              "name": "SHELLY",
              "power": 4,
              "trophies": 158
            }
          },
          {
            "tag": "#YG8LYRYVL",
            "name": "FILOU775",
            "brawler": {
              "id": 16000071,
              "name": "DOUG",
              "power": 10,
              "trophies": 157
            }
          },
          {
            "tag": "#YUJJQLR8L",
            "name": "CHARLIE\u2764\ufe0f",
            "brawler": {
              "id": 16000088,
              "name": "BUZZ LIGHTYEAR",
              "power": 11,
              "trophies": 169
            }
          },
          {
            "tag": "#P2QL8CQP0",
            "name": "sebasrian",
            "brawler": {
              "id": 16000088,
              "name": "BUZZ LIGHTYEAR",
              "power": 11,
              "trophies": 172
            }
          },
          {
            "tag": "#28YVGL22QP",
            "name": "St.Mapache",
            "brawler": {
              "id": 16000086,
              "name": "SHADE",
              "power": 6,
              "trophies": 175
            }
          },
          {
            "tag": "#2QCGCGYUU2",
            "name": "Veilleux96",
            "brawler": {
              "id": 16000077,
              "name": "LARRY & LAWRIE",
              "power": 6,
              "trophies": 177
            }
          }
        ]
      }
    },
    {
      "battleTime": "20241215T194016.000Z",
      "event": {
        "id": 15000228,
        "mode": "soloShowdown",
        "map": "Safety Center"
      },
      "battle": {
        "mode": "soloShowdown",
        "type": "ranked",
        "rank": 6,
        "trophyChange": 2,
        "players": [
          {
            "tag": "#9L8V2888V",
            "name": "chte casse",
            "brawler": {
              "id": 16000088,
              "name": "BUZZ LIGHTYEAR",
              "power": 11,
              "trophies": 183
            }
          },
          {
            "tag": "#28G89VPJCL",
            "name": "Brawler",
            "brawler": {
              "id": 16000011,
              "name": "MORTIS",
              "power": 8,
              "trophies": 165
            }
          },
          {
            "tag": "#2QU22UCRQ8",
            "name": "coopers_02",
            "brawler": {
              "id": 16000018,
              "name": "DARRYL",
              "power": 5,
              "trophies": 162
            }
          },
          {
            "tag": "#C0R8PJ0C9",
            "name": "aio",
            "brawler": {
              "id": 16000007,
              "name": "JESSIE",
              "power": 4,
              "trophies": 155
            }
          },
          {
            "tag": "#8URJVLY2C",
            "name": "Robfunmix1357",
            "brawler": {
              "id": 16000088,
              "name": "BUZZ LIGHTYEAR",
              "power": 11,
              "trophies": 155
            }
          },
          {
            "tag": "#2GL8YLVPGY",
            "name": "fettuccine",
            "brawler": {
              "id": 16000010,
              "name": "EL PRIMO",
              "power": 5,
              "trophies": 159
            }
          },
          {
            "tag": "#Y2J2P08Q2",
            "name": "DEMON_YP",
            "brawler": {
              "id": 16000019,
              "name": "PENNY",
              "power": 7,
              "trophies": 161
            }
          },
          {
            "tag": "#YQVQYJV2",
            "name": "Juan1336",
            "brawler": {
              "id": 16000075,
              "name": "MICO",
              "power": 9,
              "trophies": 177
            }
          },
          {
            "tag": "#2GLY2RPRJY",
            "name": "rizzler",
            "brawler": {
              "id": 16000088,
              "name": "BUZZ LIGHTYEAR",
              "power": 11,
              "trophies": 168
            }
          },
          {
            "tag": "#2LCLUV0J28",
            "name": "bad dawg",
            "brawler": {
              "id": 16000015,
              "name": "PIPER",
              "power": 6,
              "trophies": 173
            }
          }
        ]
      }
    },
    {
      "battleTime": "20241215T004807.000Z",
      "event": {
        "id": 15000228,
        "mode": "soloShowdown",
        "map": "Safety Center"
      },
      "battle": {
        "mode": "soloShowdown",
        "type": "ranked",
        "rank": 6,
        "trophyChange": 2,
        "players": [
          {
            "tag": "#CUCP08RGP",
            "name": "pix",
            "brawler": {
              "id": 16000088,
              "name": "BUZZ LIGHTYEAR",
              "power": 11,
              "trophies": 161
            }
          },
          {
            "tag": "#2QU0Y99U2C",
            "name": "DuckyFoots0",
            "brawler": {
              "id": 16000023,
              "name": "LEON",
              "power": 7,
              "trophies": 156
            }
          },
          {
            "tag": "#2Q9PU8U90U",
            "name": "Abeth_213",
            "brawler": {
              "id": 16000088,
              "name": "BUZZ LIGHTYEAR",
              "power": 11,
              "trophies": 150
            }
          },
          {
            "tag": "#2U9R29RYJ",
            "name": "Planadino",
            "brawler": {
              "id": 16000080,
              "name": "DRACO",
              "power": 6,
              "trophies": 157
            }
          },
          {
            "tag": "#R2UVPYG9Y",
            "name": "ternure 68",
            "brawler": {
              "id": 16000074,
              "name": "CHARLIE",
              "power": 8,
              "trophies": 157
            }
          },
          {
            "tag": "#2GL8YLVPGY",
            "name": "fettuccine",
            "brawler": {
              "id": 16000010,
              "name": "EL PRIMO",
              "power": 5,
              "trophies": 157
            }
          },
          {
            "tag": "#J2J8L9L8G",
            "name": "\u012e\u0227\u0271\u0166\u00f8\u0105\u0282\u026c\u01b4",
            "brawler": {
              "id": 16000088,
              "name": "BUZZ LIGHTYEAR",
              "power": 11,
              "trophies": 157
            }
          },
          {
            "tag": "#G0C82GL9R",
            "name": "Mortis",
            "brawler": {
              "id": 16000086,
              "name": "SHADE",
              "power": 7,
              "trophies": 160
            }
          },
          {
            "tag": "#2LL09LC08V",
            "name": "adriana",
            "brawler": {
              "id": 16000088,
              "name": "BUZZ LIGHTYEAR",
              "power": 11,
              "trophies": 152
            }
          },
          {
            "tag": "#28GLLUPCPY",
            "name": "MECHA",
            "brawler": {
              "id": 16000060,
              "name": "SAM",
              "power": 6,
              "trophies": 144
            }
          }
        ]
      }
    },
    {
      "battleTime": "20241215T004716.000Z",
      "event": {
        "id": 15000228,
        "mode": "soloShowdown",
        "map": "Safety Center"
      },
      "battle": {
        "mode": "soloShowdown",
        "type": "ranked",
        "rank": 3,
        "trophyChange": 7,
        "players": [
          {
            "tag": "#2G88PULLLQ",
            "name": "LE MACHO",
            "brawler": {
              "id": 16000010,
              "name": "EL PRIMO",
              "power": 6,
              "trophies": 148
            }
          },
          {
            "tag": "#2QL9RYJ29P",
            "name": "bob",
            "brawler": {
              "id": 16000018,
              "name": "DARRYL",
              "power": 9,
              "trophies": 140
            }
          },
          {
            "tag": "#2GL8YLVPGY",
            "name": "fettuccine",
            "brawler": {
              "id": 16000010,
              "name": "EL PRIMO",
              "power": 5,
              "trophies": 150
            }
          },
          {
            "tag": "#2QVPJGYJ2",
            "name": "PsychoBomb",
            "brawler": {
              "id": 16000088,
              "name": "BUZZ LIGHTYEAR",
              "power": 11,
              "trophies": 148
            }
          },
          {
            "tag": "#8CVRJLQ8Q",
            "name": "Post",
            "brawler": {
              "id": 16000088,
              "name": "BUZZ LIGHTYEAR",
              "power": 11,
              "trophies": 148
            }
          },
          {
            "tag": "#2G2YRGUYG2",
            "name": "ROSA",
            "brawler": {
              "id": 16000088,
              "name": "BUZZ LIGHTYEAR",
              "power": 11,
              "trophies": 140
            }
          },
          {
            "tag": "#2GG2828820",
            "name": "sigma",
            "brawler": {
              "id": 16000007,
              "name": "JESSIE",
              "power": 8,
              "trophies": 152
            }
          },
          {
            "tag": "#2QU9CYPVJR",
            "name": "DARRYL",
            "brawler": {
              "id": 16000018,
              "name": "DARRYL",
              "power": 10,
              "trophies": 148
            }
          },
          {
            "tag": "#28ULVJCQJ",
            "name": "MaalixBS",
            "brawler": {
              "id": 16000009,
              "name": "DYNAMIKE",
              "power": 6,
              "trophies": 148
            }
          },
          {
            "tag": "#2QQG088QCL",
            "name": "Doria",
            "brawler": {
              "id": 16000088,
              "name": "BUZZ LIGHTYEAR",
              "power": 11,
              "trophies": 150
            }
          }
        ]
      }
    },
    {
      "battleTime": "20241215T004525.000Z",
      "event": {
        "id": 15000228,
        "mode": "soloShowdown",
        "map": "Safety Center"
      },
      "battle": {
        "mode": "soloShowdown",
        "type": "ranked",
        "rank": 7,
        "trophyChange": 2,
        "players": [
          {
            "tag": "#J8RPCPGU",
            "name": "bob",
            "brawler": {
              "id": 16000088,
              "name": "BUZZ LIGHTYEAR",
              "power": 11,
              "trophies": 147
            }
          },
          {
            "tag": "#PPCUYV8UY",
            "name": "zetsufx",
            "brawler": {
              "id": 16000008,
              "name": "NITA",
              "power": 8,
              "trophies": 175
            }
          },
          {
            "tag": "#2C80JLP0",
            "name": "\u718a\u718a",
            "brawler": {
              "id": 16000088,
              "name": "BUZZ LIGHTYEAR",
              "power": 11,
              "trophies": 150
            }
          },
          {
            "tag": "#228UUV0PUL",
            "name": "GR. AHD\ud83c\uddf9\ud83c\uddf3",
            "brawler": {
              "id": 16000077,
              "name": "LARRY & LAWRIE",
              "power": 7,
              "trophies": 165
            }
          },
          {
            "tag": "#2QURUL0Y2U",
            "name": "\ud835\udc8b\ud835\udc90\ud835\udc94\ud835\udc86",
            "brawler": {
              "id": 16000088,
              "name": "BUZZ LIGHTYEAR",
              "power": 11,
              "trophies": 173
            }
          },
          {
            "tag": "#2QG9YUJUVV",
            "name": "imagine losing",
            "brawler": {
              "id": 16000013,
              "name": "POCO",
              "power": 7,
              "trophies": 149
            }
          },
          {
            "tag": "#2GL8YLVPGY",
            "name": "fettuccine",
            "brawler": {
              "id": 16000010,
              "name": "EL PRIMO",
              "power": 5,
              "trophies": 148
            }
          },
          {
            "tag": "#LLCUCY0RR",
            "name": "larabear6969",
            "brawler": {
              "id": 16000022,
              "name": "TICK",
              "power": 5,
              "trophies": 148
            }
          },
          {
            "tag": "#YQV2L9QJ9",
            "name": "Queso",
            "brawler": {
              "id": 16000068,
              "name": "MAISIE",
              "power": 8,
              "trophies": 168
            }
          },
          {
            "tag": "#2Y22G82990",
            "name": "\ud83e\udd2bhaha",
            "brawler": {
              "id": 16000082,
              "name": "BERRY",
              "power": 5,
              "trophies": 160
            }
          }
        ]
      }
    },
    {
      "battleTime": "20241215T004142.000Z",
      "event": {
        "id": 15000228,
        "mode": "soloShowdown",
        "map": "Safety Center"
      },
      "battle": {
        "mode": "soloShowdown",
        "type": "ranked",
        "rank": 8,
        "trophyChange": 1,
        "players": [
          {
            "tag": "#2YLY2YY2P0",
            "name": "wirtz",
            "brawler": {
              "id": 16000088,
              "name": "BUZZ LIGHTYEAR",
              "power": 11,
              "trophies": 155
            }
          },
          {
            "tag": "#2QLVYJL808",
            "name": "Yali",
            "brawler": {
              "id": 16000088,
              "name": "BUZZ LIGHTYEAR",
              "power": 11,
              "trophies": 146
            }
          },
          {
            "tag": "#20GJRJ9PQ",
            "name": "\ud835\udd6d\ud835\udd7e|\ud835\udc7a\ud835\udc68\ud835\udc7f\ud835\udc76\ud83e\udd13",
            "brawler": {
              "id": 16000088,
              "name": "BUZZ LIGHTYEAR",
              "power": 11,
              "trophies": 155
            }
          },
          {
            "tag": "#2QQRRQPJRY",
            "name": "Emilio09711",
            "brawler": {
              "id": 16000088,
              "name": "BUZZ LIGHTYEAR",
              "power": 11,
              "trophies": 140
            }
          },
          {
            "tag": "#LRYGJJVRL",
            "name": "lukita",
            "brawler": {
              "id": 16000069,
              "name": "HANK",
              "power": 6,
              "trophies": 119
            }
          },
          {
            "tag": "#2GLJYUUCLJ",
            "name": "leo",
            "brawler": {
              "id": 16000008,
              "name": "NITA",
              "power": 7,
              "trophies": 147
            }
          },
          {
            "tag": "#2GPRRVGU8L",
            "name": "Fernando",
            "brawler": {
              "id": 16000018,
              "name": "DARRYL",
              "power": 8,
              "trophies": 147
            }
          },
          {
            "tag": "#2GL8YLVPGY",
            "name": "fettuccine",
            "brawler": {
              "id": 16000010,
              "name": "EL PRIMO",
              "power": 5,
              "trophies": 147
            }
          },
          {
            "tag": "#2YR2C0J2UU",
            "name": "leBruh_James",
            "brawler": {
              "id": 16000032,
              "name": "MAX",
              "power": 1,
              "trophies": 152
            }
          },
          {
            "tag": "#YPL8PJ2U0",
            "name": "Twitch-drizzyx$",
            "brawler": {
              "id": 16000018,
              "name": "DARRYL",
              "power": 5,
              "trophies": 152
            }
          }
        ]
      }
    },
    {
      "battleTime": "20241215T003930.000Z",
      "event": {
        "id": 15000228,
        "mode": "soloShowdown",
        "map": "Safety Center"
      },
      "battle": {
        "mode": "soloShowdown",
        "type": "ranked",
        "rank": 1,
        "trophyChange": 10,
        "players": [
          {
            "tag": "#2GL8YLVPGY",
            "name": "fettuccine",
            "brawler": {
              "id": 16000010,
              "name": "EL PRIMO",
              "power": 5,
              "trophies": 137
            }
          },
          {
            "tag": "#9UPG802P2",
            "name": "\u6700\u7ec8\u5de8\u578b\u94a2\u7b4b\u94c1\u9f99\u9aa8\u70ae",
            "brawler": {
              "id": 16000006,
              "name": "BARLEY",
              "power": 6,
              "trophies": 138
            }
          },
          {
            "tag": "#9U9L020Q9",
            "name": "kie\u014222",
            "brawler": {
              "id": 16000000,
              "name": "SHELLY",
              "power": 5,
              "trophies": 144
            }
          },
          {
            "tag": "#9U0YYCC2C",
            "name": "saiko",
            "brawler": {
              "id": 16000010,
              "name": "EL PRIMO",
              "power": 6,
              "trophies": 142
            }
          },
          {
            "tag": "#9U2RRJJJR",
            "name": "3heldenhoch",
            "brawler": {
              "id": 16000003,
              "name": "BROCK",
              "power": 5,
              "trophies": 136
            }
          },
          {
            "tag": "#9U9ULJPPY",
            "name": "Em@lesssss",
            "brawler": {
              "id": 16000034,
              "name": "JACKY",
              "power": 5,
              "trophies": 131
            }
          },
          {
            "tag": "#9UPYV8RJV",
            "name": "jsksie",
            "brawler": {
              "id": 16000013,
              "name": "POCO",
              "power": 6,
              "trophies": 129
            }
          },
          {
            "tag": "#9U29YG099",
            "name": "\u0e40\u0e1a\u0e35\u0e22\u0e27Nita",
            "brawler": {
              "id": 16000014,
              "name": "BO",
              "power": 4,
              "trophies": 144
            }
          },
          {
            "tag": "#9U9V0UPYQ",
            "name": "LL|CARMELO OO",
            "brawler": {
              "id": 16000030,
              "name": "EMZ",
              "power": 6,
              "trophies": 131
            }
          },
          {
            "tag": "#9UPYJJUVQ",
            "name": "Lukas",
            "brawler": {
              "id": 16000008,
              "name": "NITA",
              "power": 5,
              "trophies": 138
            }
          }
        ]
      }
    },
    {
      "battleTime": "20241214T214011.000Z",
      "event": {
        "id": 15000228,
        "mode": "soloShowdown",
        "map": "Safety Center"
      },
      "battle": {
        "mode": "soloShowdown",
        "type": "ranked",
        "rank": 6,
        "trophyChange": 2,
        "players": [
          {
            "tag": "#2GQPQUQ9LU",
            "name": "Yeisver\ud83e\udd77\ud83c\udffd\u2694\ufe0f",
            "brawler": {
              "id": 16000088,
              "name": "BUZZ LIGHTYEAR",
              "power": 11,
              "trophies": 164
            }
          },
          {
            "tag": "#2GJJJLLJ",
            "name": "GrimLoched",
            "brawler": {
              "id": 16000088,
              "name": "BUZZ LIGHTYEAR",
              "power": 11,
              "trophies": 163
            }
          },
          {
            "tag": "#LYYUR2VJU",
            "name": "cj-cyber",
            "brawler": {
              "id": 16000088,
              "name": "BUZZ LIGHTYEAR",
              "power": 11,
              "trophies": 136
            }
          },
          {
            "tag": "#2LLGPP02RG",
            "name": "sof<3",
            "brawler": {
              "id": 16000010,
              "name": "EL PRIMO",
              "power": 8,
              "trophies": 164
            }
          },
          {
            "tag": "#2G02YY08JJ",
            "name": "Apolo",
            "brawler": {
              "id": 16000010,
              "name": "EL PRIMO",
              "power": 10,
              "trophies": 132
            }
          },
          {
            "tag": "#2GL8YLVPGY",
            "name": "fettuccine",
            "brawler": {
              "id": 16000010,
              "name": "EL PRIMO",
              "power": 5,
              "trophies": 135
            }
          },
          {
            "tag": "#GPQR0Q0GY",
            "name": "sh.wf",
            "brawler": {
              "id": 16000061,
              "name": "GUS",
              "power": 8,
              "trophies": 164
            }
          },
          {
            "tag": "#2988RVCUVP",
            "name": "bro128886",
            "brawler": {
              "id": 16000005,
              "name": "SPIKE",
              "power": 3,
              "trophies": 165
            }
          },
          {
            "tag": "#UCG0QYC0U",
            "name": "bobross1",
            "brawler": {
              "id": 16000015,
              "name": "PIPER",
              "power": 1,
              "trophies": 165
            }
          },
          {
            "tag": "#28JYJ0R0CC",
            "name": "Unrealhanger243",
            "brawler": {
              "id": 16000088,
              "name": "BUZZ LIGHTYEAR",
              "power": 11,
              "trophies": 119
            }
          }
        ]
      }
    },
    {
      "battleTime": "20241214T213858.000Z",
      "event": {
        "id": 15000228,
        "mode": "soloShowdown",
        "map": "Safety Center"
      },
      "battle": {
        "mode": "soloShowdown",
        "type": "ranked",
        "rank": 9,
        "players": [
          {
            "tag": "#2Q0V2VJ8QC",
            "name": "Water",
            "brawler": {
              "id": 16000088,
              "name": "BUZZ LIGHTYEAR",
              "power": 11,
              "trophies": 136
            }
          },
          {
            "tag": "#2QPPPQ8L22",
            "name": "kit",
            "brawler": {
              "id": 16000086,
              "name": "SHADE",
              "power": 5,
              "trophies": 136
            }
          },
          {
            "tag": "#YVVYYC0U0",
            "name": "Dripking999",
            "brawler": {
              "id": 16000088,
              "name": "BUZZ LIGHTYEAR",
              "power": 11,
              "trophies": 110
            }
          },
          {
            "tag": "#2QRGUYJQ9U",
            "name": "MoiMan",
            "brawler": {
              "id": 16000001,
              "name": "COLT",
              "power": 1,
              "trophies": 135
            }
          },
          {
            "tag": "#28JU0C0RRC",
            "name": "Rug",
            "brawler": {
              "id": 16000010,
              "name": "EL PRIMO",
              "power": 5,
              "trophies": 110
            }
          },
          {
            "tag": "#2QJC99RV0G",
            "name": "bfausty3",
            "brawler": {
              "id": 16000036,
              "name": "NANI",
              "power": 1,
              "trophies": 129
            }
          },
          {
            "tag": "#2GGY8YLVR9",
            "name": "PEDRO01",
            "brawler": {
              "id": 16000010,
              "name": "EL PRIMO",
              "power": 4,
              "trophies": 129
            }
          },
          {
            "tag": "#YGQJVP8YL",
            "name": "SB|Griffs Tip",
            "brawler": {
              "id": 16000008,
              "name": "NITA",
              "power": 5,
              "trophies": 136
            }
          },
          {
            "tag": "#2GL8YLVPGY",
            "name": "fettuccine",
            "brawler": {
              "id": 16000010,
              "name": "EL PRIMO",
              "power": 5,
              "trophies": 135
            }
          },
          {
            "tag": "#2GCYG8LCQC",
            "name": "zaizo",
            "brawler": {
              "id": 16000088,
              "name": "BUZZ LIGHTYEAR",
              "power": 11,
              "trophies": 136
            }
          }
        ]
      }
    },
    {
      "battleTime": "20241214T213454.000Z",
      "event": {
        "id": 15000228,
        "mode": "soloShowdown",
        "map": "Safety Center"
      },
      "battle": {
        "mode": "soloShowdown",
        "type": "ranked",
        "rank": 7,
        "trophyChange": 2,
        "players": [
          {
            "tag": "#YR9V2UGCQ",
            "name": "Pro Master Ella",
            "brawler": {
              "id": 16000088,
              "name": "BUZZ LIGHTYEAR",
              "power": 11,
              "trophies": 131
            }
          },
          {
            "tag": "#2QV2VG0VRC",
            "name": "TheRizzyRat",
            "brawler": {
              "id": 16000088,
              "name": "BUZZ LIGHTYEAR",
              "power": 11,
              "trophies": 131
            }
          },
          {
            "tag": "#2QGGVRVJ8L",
            "name": "YT/Kenji",
            "brawler": {
              "id": 16000088,
              "name": "BUZZ LIGHTYEAR",
              "power": 11,
              "trophies": 131
            }
          },
          {
            "tag": "#2GL02JJ0QR",
            "name": "mariyuyis14",
            "brawler": {
              "id": 16000008,
              "name": "NITA",
              "power": 1,
              "trophies": 130
            }
          },
          {
            "tag": "#29VCQCJCU",
            "name": "AcidBoyJack",
            "brawler": {
              "id": 16000088,
              "name": "BUZZ LIGHTYEAR",
              "power": 11,
              "trophies": 130
            }
          },
          {
            "tag": "#2QQJPCJ9QG",
            "name": "slimjim",
            "brawler": {
              "id": 16000088,
              "name": "BUZZ LIGHTYEAR",
              "power": 11,
              "trophies": 115
            }
          },
          {
            "tag": "#2GL8YLVPGY",
            "name": "fettuccine",
            "brawler": {
              "id": 16000010,
              "name": "EL PRIMO",
              "power": 5,
              "trophies": 133
            }
          },
          {
            "tag": "#2GP898CCGP",
            "name": "cloverleaf",
            "brawler": {
              "id": 16000088,
              "name": "BUZZ LIGHTYEAR",
              "power": 11,
              "trophies": 130
            }
          },
          {
            "tag": "#2QLJ09GGR2",
            "name": "SIEGERT ES Him",
            "brawler": {
              "id": 16000081,
              "name": "LILY",
              "power": 3,
              "trophies": 124
            }
          },
          {
            "tag": "#2QVVV29L90",
            "name": "seedjay",
            "brawler": {
              "id": 16000000,
              "name": "SHELLY",
              "power": 7,
              "trophies": 130
            }
          }
        ]
      }
    },
    {
      "battleTime": "20241214T213404.000Z",
      "event": {
        "id": 15000228,
        "mode": "soloShowdown",
        "map": "Safety Center"
      },
      "battle": {
        "mode": "soloShowdown",
        "type": "ranked",
        "rank": 6,
        "trophyChange": 2,
        "players": [
          {
            "tag": "#8GJ889808",
            "name": "EMMAX",
            "brawler": {
              "id": 16000088,
              "name": "BUZZ LIGHTYEAR",
              "power": 11,
              "trophies": 136
            }
          },
          {
            "tag": "#YPU090Y2C",
            "name": "Itachi",
            "brawler": {
              "id": 16000017,
              "name": "TARA",
              "power": 7,
              "trophies": 135
            }
          },
          {
            "tag": "#28G9CVLRU8",
            "name": "daddyhayhay",
            "brawler": {
              "id": 16000088,
              "name": "BUZZ LIGHTYEAR",
              "power": 11,
              "trophies": 147
            }
          },
          {
            "tag": "#2QGVLRR99U",
            "name": "mint chocolate",
            "brawler": {
              "id": 16000016,
              "name": "PAM",
              "power": 3,
              "trophies": 138
            }
          },
          {
            "tag": "#2QUY0VQQJU",
            "name": "sigma bro",
            "brawler": {
              "id": 16000011,
              "name": "MORTIS",
              "power": 3,
              "trophies": 134
            }
          },
          {
            "tag": "#2GL8YLVPGY",
            "name": "fettuccine",
            "brawler": {
              "id": 16000010,
              "name": "EL PRIMO",
              "power": 5,
              "trophies": 131
            }
          },
          {
            "tag": "#2Q2Q8LQCPL",
            "name": "steve",
            "brawler": {
              "id": 16000000,
              "name": "SHELLY",
              "power": 8,
              "trophies": 121
            }
          },
          {
            "tag": "#2LUQYUYC9C",
            "name": "reece",
            "brawler": {
              "id": 16000086,
              "name": "SHADE",
              "power": 10,
              "trophies": 130
            }
          },
          {
            "tag": "#8Q8PPQP9V",
            "name": "DOM",
            "brawler": {
              "id": 16000088,
              "name": "BUZZ LIGHTYEAR",
              "power": 11,
              "trophies": 122
            }
          },
          {
            "tag": "#2LVYCG8CL2",
            "name": "Obsidian",
            "brawler": {
              "id": 16000007,
              "name": "JESSIE",
              "power": 8,
              "trophies": 126
            }
          }
        ]
      }
    },
    {
      "battleTime": "20241214T061631.000Z",
      "event": {
        "id": 15000015,
        "mode": "soloShowdown",
        "map": "Rockwall Brawl"
      },
      "battle": {
        "mode": "soloShowdown",
        "type": "ranked",
        "rank": 6,
        "trophyChange": 2,
        "players": [
          {
            "tag": "#YPYVGGP28",
            "name": "SupaNika",
            "brawler": {
              "id": 16000088,
              "name": "BUZZ LIGHTYEAR",
              "power": 11,
              "trophies": 134
            }
          },
          {
            "tag": "#2YLL0L99UR",
            "name": "totis31 \ud83d\udc23\ud83e\udd89",
            "brawler": {
              "id": 16000030,
              "name": "EMZ",
              "power": 6,
              "trophies": 125
            }
          },
          {
            "tag": "#2QQ8PVQCY9",
            "name": "Fang",
            "brawler": {
              "id": 16000088,
              "name": "BUZZ LIGHTYEAR",
              "power": 11,
              "trophies": 116
            }
          },
          {
            "tag": "#VYC9URLQ0",
            "name": "margielaa",
            "brawler": {
              "id": 16000027,
              "name": "8-BIT",
              "power": 4,
              "trophies": 136
            }
          },
          {
            "tag": "#Q9PCUVQRJ",
            "name": "Ben4",
            "brawler": {
              "id": 16000088,
              "name": "BUZZ LIGHTYEAR",
              "power": 11,
              "trophies": 149
            }
          },
          {
            "tag": "#2GL8YLVPGY",
            "name": "fettuccine",
            "brawler": {
              "id": 16000010,
              "name": "EL PRIMO",
              "power": 5,
              "trophies": 129
            }
          },
          {
            "tag": "#29PU0RVC8",
            "name": "EMOBOI",
            "brawler": {
              "id": 16000012,
              "name": "CROW",
              "power": 1,
              "trophies": 123
            }
          },
          {
            "tag": "#JRRGUUR2P",
            "name": "vanhalen",
            "brawler": {
              "id": 16000088,
              "name": "BUZZ LIGHTYEAR",
              "power": 11,
              "trophies": 154
            }
          },
          {
            "tag": "#LQGJJR9QQ",
            "name": "p\u0365oc\u0363o\u036b \u1d43 \u1d4d\u1d52\u1d48",
            "brawler": {
              "id": 16000028,
              "name": "SANDY",
              "power": 6,
              "trophies": 132
            }
          },
          {
            "tag": "#2GCC90Y80Q",
            "name": "BR3NZ!",
            "brawler": {
              "id": 16000008,
              "name": "NITA",
              "power": 5,
              "trophies": 143
            }
          }
        ]
      }
    },
    {
      "battleTime": "20241213T174553.000Z",
      "event": {
        "id": 15000701,
        "mode": "soloShowdown",
        "map": "Marksman's Paradise"
      },
      "battle": {
        "mode": "soloShowdown",
        "type": "ranked",
        "rank": 8,
        "trophyChange": 1,
        "players": [
          {
            "tag": "#2L2G9228CP",
            "name": "lil chubbybacon",
            "brawler": {
              "id": 16000088,
              "name": "BUZZ LIGHTYEAR",
              "power": 11,
              "trophies": 127
            }
          },
          {
            "tag": "#2L88LG99LV",
            "name": "anna",
            "brawler": {
              "id": 16000039,
              "name": "COLETTE",
              "power": 9,
              "trophies": 126
            }
          },
          {
            "tag": "#PPU0GY8Q9",
            "name": "Skarlet.476",
            "brawler": {
              "id": 16000077,
              "name": "LARRY & LAWRIE",
              "power": 9,
              "trophies": 126
            }
          },
          {
            "tag": "#LQQ9QL2V0",
            "name": "patoloco\ud83e\udd76\ud83d\udc7b",
            "brawler": {
              "id": 16000086,
              "name": "SHADE",
              "power": 6,
              "trophies": 124
            }
          },
          {
            "tag": "#2GLG0VC0LJ",
            "name": "jslim",
            "brawler": {
              "id": 16000088,
              "name": "BUZZ LIGHTYEAR",
              "power": 11,
              "trophies": 128
            }
          },
          {
            "tag": "#2QCV2LR0JJ",
            "name": "cherem",
            "brawler": {
              "id": 16000023,
              "name": "LEON",
              "power": 4,
              "trophies": 127
            }
          },
          {
            "tag": "#9VVPGUGJ2",
            "name": "CzTlacuaches",
            "brawler": {
              "id": 16000020,
              "name": "FRANK",
              "power": 9,
              "trophies": 127
            }
          },
          {
            "tag": "#2GL8YLVPGY",
            "name": "fettuccine",
            "brawler": {
              "id": 16000010,
              "name": "EL PRIMO",
              "power": 5,
              "trophies": 128
            }
          },
          {
            "tag": "#2Y2RJRYJVL",
            "name": "gerald",
            "brawler": {
              "id": 16000020,
              "name": "FRANK",
              "power": 8,
              "trophies": 126
            }
          },
          {
            "tag": "#2Q0YYQQ8GP",
            "name": "samu",
            "brawler": {
              "id": 16000088,
              "name": "BUZZ LIGHTYEAR",
              "power": 11,
              "trophies": 129
            }
          }
        ]
      }
    },
    {
      "battleTime": "20241213T174509.000Z",
      "event": {
        "id": 15000701,
        "mode": "soloShowdown",
        "map": "Marksman's Paradise"
      },
      "battle": {
        "mode": "soloShowdown",
        "type": "ranked",
        "rank": 8,
        "trophyChange": 1,
        "players": [
          {
            "tag": "#GV2C9LV",
            "name": "iAdrian \ud83d\udd25",
            "brawler": {
              "id": 16000088,
              "name": "BUZZ LIGHTYEAR",
              "power": 11,
              "trophies": 128
            }
          },
          {
            "tag": "#2LJCRG8Q89",
            "name": "me a twirker",
            "brawler": {
              "id": 16000088,
              "name": "BUZZ LIGHTYEAR",
              "power": 11,
              "trophies": 130
            }
          },
          {
            "tag": "#20VVVV0J",
            "name": "Acosta7u7",
            "brawler": {
              "id": 16000088,
              "name": "BUZZ LIGHTYEAR",
              "power": 11,
              "trophies": 130
            }
          },
          {
            "tag": "#8Y8VJL9GJ",
            "name": "fin",
            "brawler": {
              "id": 16000088,
              "name": "BUZZ LIGHTYEAR",
              "power": 11,
              "trophies": 137
            }
          },
          {
            "tag": "#28QVQ8R80Q",
            "name": "grippy",
            "brawler": {
              "id": 16000088,
              "name": "BUZZ LIGHTYEAR",
              "power": 11,
              "trophies": 129
            }
          },
          {
            "tag": "#QYCYR8C0Y",
            "name": "Raymidio",
            "brawler": {
              "id": 16000088,
              "name": "BUZZ LIGHTYEAR",
              "power": 11,
              "trophies": 123
            }
          },
          {
            "tag": "#RQCV98PV8",
            "name": "marciano",
            "brawler": {
              "id": 16000088,
              "name": "BUZZ LIGHTYEAR",
              "power": 11,
              "trophies": 144
            }
          },
          {
            "tag": "#2GL8YLVPGY",
            "name": "fettuccine",
            "brawler": {
              "id": 16000010,
              "name": "EL PRIMO",
              "power": 5,
              "trophies": 127
            }
          },
          {
            "tag": "#Q28JR0VVC",
            "name": "Dingoshart",
            "brawler": {
              "id": 16000027,
              "name": "8-BIT",
              "power": 8,
              "trophies": 130
            }
          },
          {
            "tag": "#QGQCUJ9QL",
            "name": "REM",
            "brawler": {
              "id": 16000005,
              "name": "SPIKE",
              "power": 6,
              "trophies": 123
            }
          }
        ]
      }
    },
    {
      "battleTime": "20241213T174306.000Z",
      "event": {
        "id": 15000701,
        "mode": "soloShowdown",
        "map": "Marksman's Paradise"
      },
      "battle": {
        "mode": "soloShowdown",
        "type": "ranked",
        "rank": 2,
        "trophyChange": 13,
        "players": [
          {
            "tag": "#9U9CU9LPY",
            "name": "lucca el pro",
            "brawler": {
              "id": 16000014,
              "name": "BO",
              "power": 6,
              "trophies": 110
            }
          },
          {
            "tag": "#2GL8YLVPGY",
            "name": "fettuccine",
            "brawler": {
              "id": 16000010,
              "name": "EL PRIMO",
              "power": 5,
              "trophies": 114
            }
          },
          {
            "tag": "#9U9G8CYR9",
            "name": "PRIMROSE",
            "brawler": {
              "id": 16000034,
              "name": "JACKY",
              "power": 4,
              "trophies": 105
            }
          },
          {
            "tag": "#9U22J0JUV",
            "name": "sta#sss",
            "brawler": {
              "id": 16000006,
              "name": "BARLEY",
              "power": 5,
              "trophies": 121
            }
          },
          {
            "tag": "#9UP9JQ8YQ",
            "name": "spiderman989",
            "brawler": {
              "id": 16000013,
              "name": "POCO",
              "power": 4,
              "trophies": 115
            }
          },
          {
            "tag": "#9U0PC0QJY",
            "name": "\u0646\u0627\u0635\u0631",
            "brawler": {
              "id": 16000008,
              "name": "NITA",
              "power": 6,
              "trophies": 110
            }
          },
          {
            "tag": "#9UP2RRYLV",
            "name": "ON/M4T3US",
            "brawler": {
              "id": 16000007,
              "name": "JESSIE",
              "power": 4,
              "trophies": 112
            }
          },
          {
            "tag": "#9U0P2Y29Q",
            "name": "SK|shinobu \ud83e\udd8b",
            "brawler": {
              "id": 16000030,
              "name": "EMZ",
              "power": 6,
              "trophies": 106
            }
          },
          {
            "tag": "#9U9JGGJUV",
            "name": "distant",
            "brawler": {
              "id": 16000010,
              "name": "EL PRIMO",
              "power": 6,
              "trophies": 121
            }
          },
          {
            "tag": "#9U9Y008GY",
            "name": "/gg/zen",
            "brawler": {
              "id": 16000003,
              "name": "BROCK",
              "power": 4,
              "trophies": 123
            }
          }
        ]
      }
    },
    {
      "battleTime": "20241213T174139.000Z",
      "event": {
        "id": 15000701,
        "mode": "soloShowdown",
        "map": "Marksman's Paradise"
      },
      "battle": {
        "mode": "soloShowdown",
        "type": "ranked",
        "rank": 1,
        "trophyChange": 15,
        "players": [
          {
            "tag": "#2GL8YLVPGY",
            "name": "fettuccine",
            "brawler": {
              "id": 16000010,
              "name": "EL PRIMO",
              "power": 5,
              "trophies": 99
            }
          },
          {
            "tag": "#9U29GV2CQ",
            "name": "\u0441\u0430\u0448\u043a\u0430\ud83d\udc9f",
            "brawler": {
              "id": 16000008,
              "name": "NITA",
              "power": 4,
              "trophies": 107
            }
          },
          {
            "tag": "#9U88Q89UR",
            "name": "\u0434\u0430\u043d\u0435\u043a \u043e\u0431\u044b\u0447\u043d\u044b\u0439",
            "brawler": {
              "id": 16000014,
              "name": "BO",
              "power": 4,
              "trophies": 97
            }
          },
          {
            "tag": "#9U289PLGY",
            "name": "joaquin",
            "brawler": {
              "id": 16000010,
              "name": "EL PRIMO",
              "power": 5,
              "trophies": 90
            }
          },
          {
            "tag": "#9U8YRP9R9",
            "name": "\u30b3\u30f3\u30d6\u3055\u3093",
            "brawler": {
              "id": 16000003,
              "name": "BROCK",
              "power": 6,
              "trophies": 107
            }
          },
          {
            "tag": "#9U99GJ8RQ",
            "name": "\u0431\u0438\u0433 \u0434\u0438\u043a",
            "brawler": {
              "id": 16000007,
              "name": "JESSIE",
              "power": 5,
              "trophies": 98
            }
          },
          {
            "tag": "#9UP08RRCQ",
            "name": "Luigox",
            "brawler": {
              "id": 16000013,
              "name": "POCO",
              "power": 5,
              "trophies": 94
            }
          },
          {
            "tag": "#9U2U9PYGR",
            "name": "pinkstink",
            "brawler": {
              "id": 16000034,
              "name": "JACKY",
              "power": 4,
              "trophies": 106
            }
          },
          {
            "tag": "#9U0QPLRRC",
            "name": "~LUZE~",
            "brawler": {
              "id": 16000000,
              "name": "SHELLY",
              "power": 4,
              "trophies": 106
            }
          },
          {
            "tag": "#9U9RCLPQC",
            "name": "puuki",
            "brawler": {
              "id": 16000006,
              "name": "BARLEY",
              "power": 4,
              "trophies": 101
            }
          }
        ]
      }
    },
    {
      "battleTime": "20241213T173909.000Z",
      "event": {
        "id": 15000701,
        "mode": "soloShowdown",
        "map": "Marksman's Paradise"
      },
      "battle": {
        "mode": "soloShowdown",
        "type": "ranked",
        "rank": 1,
        "trophyChange": 15,
        "players": [
          {
            "tag": "#2GL8YLVPGY",
            "name": "fettuccine",
            "brawler": {
              "id": 16000010,
              "name": "EL PRIMO",
              "power": 5,
              "trophies": 84
            }
          },
          {
            "tag": "#9U8UP9899",
            "name": "schiappanumero1",
            "brawler": {
              "id": 16000030,
              "name": "EMZ",
              "power": 6,
              "trophies": 81
            }
          },
          {
            "tag": "#9U2UC28QC",
            "name": "Sr Gollias 2023",
            "brawler": {
              "id": 16000014,
              "name": "BO",
              "power": 5,
              "trophies": 88
            }
          },
          {
            "tag": "#9UP0QJ99Q",
            "name": "lso",
            "brawler": {
              "id": 16000003,
              "name": "BROCK",
              "power": 6,
              "trophies": 84
            }
          },
          {
            "tag": "#9U8VPU0LR",
            "name": "Exaudius",
            "brawler": {
              "id": 16000010,
              "name": "EL PRIMO",
              "power": 6,
              "trophies": 85
            }
          },
          {
            "tag": "#9UP9G8Q9Q",
            "name": "boxmuncher",
            "brawler": {
              "id": 16000034,
              "name": "JACKY",
              "power": 5,
              "trophies": 83
            }
          },
          {
            "tag": "#9U0GPPR2C",
            "name": "Olaf",
            "brawler": {
              "id": 16000007,
              "name": "JESSIE",
              "power": 5,
              "trophies": 83
            }
          },
          {
            "tag": "#9UPGJJ2RC",
            "name": "CROW",
            "brawler": {
              "id": 16000006,
              "name": "BARLEY",
              "power": 5,
              "trophies": 82
            }
          },
          {
            "tag": "#9U8808UPY",
            "name": "Chrome Flow",
            "brawler": {
              "id": 16000013,
              "name": "POCO",
              "power": 4,
              "trophies": 79
            }
          },
          {
            "tag": "#9U22YPQG2",
            "name": "Basil",
            "brawler": {
              "id": 16000000,
              "name": "SHELLY",
              "power": 6,
              "trophies": 89
            }
          }
        ]
      }
    },
    {
      "battleTime": "20241213T173635.000Z",
      "event": {
        "id": 15000701,
        "mode": "soloShowdown",
        "map": "Marksman's Paradise"
      },
      "battle": {
        "mode": "soloShowdown",
        "type": "ranked",
        "rank": 2,
        "trophyChange": 13,
        "players": [
          {
            "tag": "#9U9J9JJJR",
            "name": "danya",
            "brawler": {
              "id": 16000014,
              "name": "BO",
              "power": 5,
              "trophies": 70
            }
          },
          {
            "tag": "#2GL8YLVPGY",
            "name": "fettuccine",
            "brawler": {
              "id": 16000010,
              "name": "EL PRIMO",
              "power": 5,
              "trophies": 71
            }
          },
          {
            "tag": "#9U9U282JV",
            "name": "heitor{OL}",
            "brawler": {
              "id": 16000003,
              "name": "BROCK",
              "power": 5,
              "trophies": 73
            }
          },
          {
            "tag": "#9U9PQ8V0R",
            "name": "KING\ud83c\uddf4\ud83c\uddf2",
            "brawler": {
              "id": 16000010,
              "name": "EL PRIMO",
              "power": 6,
              "trophies": 77
            }
          },
          {
            "tag": "#9UPGJ8YP2",
            "name": "Uniro",
            "brawler": {
              "id": 16000000,
              "name": "SHELLY",
              "power": 5,
              "trophies": 73
            }
          },
          {
            "tag": "#9U2UUP9G2",
            "name": "makotse",
            "brawler": {
              "id": 16000034,
              "name": "JACKY",
              "power": 5,
              "trophies": 71
            }
          },
          {
            "tag": "#9UPP282LY",
            "name": "adrian_stars",
            "brawler": {
              "id": 16000013,
              "name": "POCO",
              "power": 5,
              "trophies": 77
            }
          },
          {
            "tag": "#9U9VJ0GPY",
            "name": "yudi",
            "brawler": {
              "id": 16000007,
              "name": "JESSIE",
              "power": 4,
              "trophies": 71
            }
          },
          {
            "tag": "#9U9VQU8Q9",
            "name": "Lil-Shimury",
            "brawler": {
              "id": 16000030,
              "name": "EMZ",
              "power": 5,
              "trophies": 80
            }
          },
          {
            "tag": "#9UP28C2G2",
            "name": "Rosee",
            "brawler": {
              "id": 16000008,
              "name": "NITA",
              "power": 4,
              "trophies": 68
            }
          }
        ]
      }
    },
    {
      "battleTime": "20241213T173444.000Z",
      "event": {
        "id": 15000701,
        "mode": "soloShowdown",
        "map": "Marksman's Paradise"
      },
      "battle": {
        "mode": "soloShowdown",
        "type": "ranked",
        "rank": 1,
        "trophyChange": 15,
        "players": [
          {
            "tag": "#2GL8YLVPGY",
            "name": "fettuccine",
            "brawler": {
              "id": 16000010,
              "name": "EL PRIMO",
              "power": 5,
              "trophies": 56
            }
          },
          {
            "tag": "#9UPGCCVJY",
            "name": "\u043a\u0438\u0440\u0438\u043b",
            "brawler": {
              "id": 16000014,
              "name": "BO",
              "power": 5,
              "trophies": 49
            }
          },
          {
            "tag": "#9U8GQQ8C9",
            "name": "raiskaya",
            "brawler": {
              "id": 16000034,
              "name": "JACKY",
              "power": 6,
              "trophies": 53
            }
          },
          {
            "tag": "#9U8LGCQJV",
            "name": "KoningHelmond",
            "brawler": {
              "id": 16000030,
              "name": "EMZ",
              "power": 5,
              "trophies": 49
            }
          },
          {
            "tag": "#9U20YJQ02",
            "name": "ms",
            "brawler": {
              "id": 16000008,
              "name": "NITA",
              "power": 5,
              "trophies": 50
            }
          },
          {
            "tag": "#9U8YC0VJV",
            "name": "Senior Makasso",
            "brawler": {
              "id": 16000010,
              "name": "EL PRIMO",
              "power": 4,
              "trophies": 64
            }
          },
          {
            "tag": "#9U0L2VYCQ",
            "name": "\uba39\uc148",
            "brawler": {
              "id": 16000007,
              "name": "JESSIE",
              "power": 6,
              "trophies": 51
            }
          },
          {
            "tag": "#9U2QGVCGR",
            "name": "Tw\u00f3j stary",
            "brawler": {
              "id": 16000006,
              "name": "BARLEY",
              "power": 5,
              "trophies": 65
            }
          },
          {
            "tag": "#9U89JY9GR",
            "name": "maybe_creker",
            "brawler": {
              "id": 16000003,
              "name": "BROCK",
              "power": 5,
              "trophies": 53
            }
          },
          {
            "tag": "#9U8VJJ98Y",
            "name": "MALIBARO",
            "brawler": {
              "id": 16000013,
              "name": "POCO",
              "power": 4,
              "trophies": 57
            }
          }
        ]
      }
    },
    {
      "battleTime": "20241213T173255.000Z",
      "event": {
        "id": 15000701,
        "mode": "soloShowdown",
        "map": "Marksman's Paradise"
      },
      "battle": {
        "mode": "soloShowdown",
        "type": "ranked",
        "rank": 1,
        "trophyChange": 14,
        "players": [
          {
            "tag": "#2GL8YLVPGY",
            "name": "fettuccine",
            "brawler": {
              "id": 16000010,
              "name": "EL PRIMO",
              "power": 5,
              "trophies": 42
            }
          },
          {
            "tag": "#9U8RRYPRQ",
            "name": "terinedeguepe2",
            "brawler": {
              "id": 16000014,
              "name": "BO",
              "power": 5,
              "trophies": 56
            }
          },
          {
            "tag": "#9UP9YGYJV",
            "name": "TUMBALACASAMAMI",
            "brawler": {
              "id": 16000003,
              "name": "BROCK",
              "power": 4,
              "trophies": 40
            }
          },
          {
            "tag": "#9UY080J2Q",
            "name": "\ube0c\ub864\ub7ec\ub2d8",
            "brawler": {
              "id": 16000034,
              "name": "JACKY",
              "power": 6,
              "trophies": 56
            }
          },
          {
            "tag": "#9U9LVYURQ",
            "name": "\u0e40\u0e15\u0e47\u0e21\u0e15\u0e35\u0e19",
            "brawler": {
              "id": 16000010,
              "name": "EL PRIMO",
              "power": 4,
              "trophies": 56
            }
          },
          {
            "tag": "#9UP908QUR",
            "name": "KFM|KB\ud83d\udc1d",
            "brawler": {
              "id": 16000008,
              "name": "NITA",
              "power": 4,
              "trophies": 40
            }
          },
          {
            "tag": "#9UP2CLP99",
            "name": "lazer",
            "brawler": {
              "id": 16000030,
              "name": "EMZ",
              "power": 4,
              "trophies": 56
            }
          },
          {
            "tag": "#9U2VG89PR",
            "name": "\ub098\ube44\ube44\uc9c0",
            "brawler": {
              "id": 16000007,
              "name": "JESSIE",
              "power": 4,
              "trophies": 40
            }
          },
          {
            "tag": "#9UPJL8RU2",
            "name": "reedsterrrr",
            "brawler": {
              "id": 16000000,
              "name": "SHELLY",
              "power": 6,
              "trophies": 56
            }
          },
          {
            "tag": "#9UPYCQV29",
            "name": "Fridg",
            "brawler": {
              "id": 16000006,
              "name": "BARLEY",
              "power": 5,
              "trophies": 56
            }
          }
        ]
      }
    },
    {
      "battleTime": "20241213T173128.000Z",
      "event": {
        "id": 15000701,
        "mode": "soloShowdown",
        "map": "Marksman's Paradise"
      },
      "battle": {
        "mode": "soloShowdown",
        "type": "ranked",
        "rank": 1,
        "trophyChange": 13,
        "players": [
          {
            "tag": "#2GL8YLVPGY",
            "name": "fettuccine",
            "brawler": {
              "id": 16000010,
              "name": "EL PRIMO",
              "power": 5,
              "trophies": 29
            }
          },
          {
            "tag": "#9U92920JR",
            "name": "JACOPOGIANNETTI",
            "brawler": {
              "id": 16000007,
              "name": "JESSIE",
              "power": 5,
              "trophies": 40
            }
          },
          {
            "tag": "#9U298LQG2",
            "name": "E_456654",
            "brawler": {
              "id": 16000013,
              "name": "POCO",
              "power": 5,
              "trophies": 40
            }
          },
          {
            "tag": "#9U0GVJP0V",
            "name": "node_modules",
            "brawler": {
              "id": 16000010,
              "name": "EL PRIMO",
              "power": 5,
              "trophies": 32
            }
          },
          {
            "tag": "#9U0UVLQ8Y",
            "name": "F.C. Exequiel\u2122",
            "brawler": {
              "id": 16000034,
              "name": "JACKY",
              "power": 5,
              "trophies": 32
            }
          },
          {
            "tag": "#9U28CUCLV",
            "name": "tomas milyam",
            "brawler": {
              "id": 16000014,
              "name": "BO",
              "power": 5,
              "trophies": 24
            }
          },
          {
            "tag": "#9UPLGJ099",
            "name": "???",
            "brawler": {
              "id": 16000003,
              "name": "BROCK",
              "power": 4,
              "trophies": 40
            }
          },
          {
            "tag": "#9UPVYR9U2",
            "name": "BONOX4",
            "brawler": {
              "id": 16000000,
              "name": "SHELLY",
              "power": 6,
              "trophies": 32
            }
          },
          {
            "tag": "#9U9P9QRVC",
            "name": "\ud83e\udd2b\ud83e\uddcf\u200d\u2642\ufe0fMICAH",
            "brawler": {
              "id": 16000030,
              "name": "EMZ",
              "power": 5,
              "trophies": 32
            }
          },
          {
            "tag": "#9U20PRYYC",
            "name": "peytonbobo",
            "brawler": {
              "id": 16000008,
              "name": "NITA",
              "power": 6,
              "trophies": 32
            }
          }
        ]
      }
    },
    {
      "battleTime": "20241213T172757.000Z",
      "event": {
        "id": 15000701,
        "mode": "soloShowdown",
        "map": "Marksman's Paradise"
      },
      "battle": {
        "mode": "soloShowdown",
        "type": "ranked",
        "rank": 1,
        "trophyChange": 12,
        "players": [
          {
            "tag": "#2GL8YLVPGY",
            "name": "fettuccine",
            "brawler": {
              "id": 16000010,
              "name": "EL PRIMO",
              "power": 1,
              "trophies": 17
            }
          },
          {
            "tag": "#9U20C22UR",
            "name": "rusa pro",
            "brawler": {
              "id": 16000034,
              "name": "JACKY",
              "power": 2,
              "trophies": 24
            }
          },
          {
            "tag": "#9UP82V9U2",
            "name": "renato",
            "brawler": {
              "id": 16000010,
              "name": "EL PRIMO",
              "power": 1,
              "trophies": 32
            }
          },
          {
            "tag": "#9UPJGU8UV",
            "name": "\ud558\ub9ac\ubcf4",
            "brawler": {
              "id": 16000003,
              "name": "BROCK",
              "power": 1,
              "trophies": 24
            }
          },
          {
            "tag": "#9U8PRGQG2",
            "name": "Paul",
            "brawler": {
              "id": 16000014,
              "name": "BO",
              "power": 1,
              "trophies": 24
            }
          },
          {
            "tag": "#9U2UC28QC",
            "name": "Sr Gollias 2023",
            "brawler": {
              "id": 16000013,
              "name": "POCO",
              "power": 2,
              "trophies": 16
            }
          },
          {
            "tag": "#9U2GLQGL2",
            "name": "HIAGO777",
            "brawler": {
              "id": 16000030,
              "name": "EMZ",
              "power": 1,
              "trophies": 16
            }
          },
          {
            "tag": "#9U8VCYLLR",
            "name": "\u0432\u0438\u043a\u0430 \u043f\u0440\u043e",
            "brawler": {
              "id": 16000007,
              "name": "JESSIE",
              "power": 2,
              "trophies": 16
            }
          },
          {
            "tag": "#9U08GCCRC",
            "name": "\u0434\u0430\u0440\u043a",
            "brawler": {
              "id": 16000008,
              "name": "NITA",
              "power": 1,
              "trophies": 32
            }
          },
          {
            "tag": "#9UPQV9CJV",
            "name": "Messi Baba pri",
            "brawler": {
              "id": 16000006,
              "name": "BARLEY",
              "power": 1,
              "trophies": 16
            }
          }
        ]
      }
    },
    {
      "battleTime": "20241213T172517.000Z",
      "event": {
        "id": 15000701,
        "mode": "soloShowdown",
        "map": "Marksman's Paradise"
      },
      "battle": {
        "mode": "soloShowdown",
        "type": "ranked",
        "rank": 2,
        "trophyChange": 9,
        "players": [
          {
            "tag": "#9U9UUR9LY",
            "name": "Michael_187",
            "brawler": {
              "id": 16000008,
              "name": "NITA",
              "power": 1,
              "trophies": 16
            }
          },
          {
            "tag": "#2GL8YLVPGY",
            "name": "fettuccine",
            "brawler": {
              "id": 16000010,
              "name": "EL PRIMO",
              "power": 1,
              "trophies": 8
            }
          },
          {
            "tag": "#9U20C22UR",
            "name": "rusa pro",
            "brawler": {
              "id": 16000014,
              "name": "BO",
              "power": 2,
              "trophies": 8
            }
          },
          {
            "tag": "#9U2LYGYV9",
            "name": "FrankTode\u010dkoo",
            "brawler": {
              "id": 16000034,
              "name": "JACKY",
              "power": 1,
              "trophies": 0
            }
          },
          {
            "tag": "#9U0QQ9VG2",
            "name": "Finn5",
            "brawler": {
              "id": 16000003,
              "name": "BROCK",
              "power": 1,
              "trophies": 0
            }
          },
          {
            "tag": "#9U2GRCVG2",
            "name": "sugarhilloblck",
            "brawler": {
              "id": 16000030,
              "name": "EMZ",
              "power": 1,
              "trophies": 8
            }
          },
          {
            "tag": "#9U2PPL8PV",
            "name": "EasyHotyorch90s",
            "brawler": {
              "id": 16000010,
              "name": "EL PRIMO",
              "power": 1,
              "trophies": 8
            }
          },
          {
            "tag": "#9UPQGRR8Y",
            "name": "dan0n",
            "brawler": {
              "id": 16000006,
              "name": "BARLEY",
              "power": 1,
              "trophies": 0
            }
          },
          {
            "tag": "#9U9ULU8L2",
            "name": "momo",
            "brawler": {
              "id": 16000000,
              "name": "SHELLY",
              "power": 2,
              "trophies": 0
            }
          },
          {
            "tag": "#9UPP0UY8V",
            "name": "\ubc15\uc950",
            "brawler": {
              "id": 16000007,
              "name": "JESSIE",
              "power": 1,
              "trophies": 0
            }
          }
        ]
      }
    },
    {
      "battleTime": "20241213T172341.000Z",
      "event": {
        "id": 15000051,
        "mode": "brawlBall",
        "map": "Super Beach"
      },
      "battle": {
        "mode": "brawlBall",
        "type": "ranked",
        "result": "victory",
        "duration": 28,
        "trophyChange": 8,
        "starPlayer": {
          "tag": "#CJU28JQC",
          "name": "lil cuzzo",
          "brawler": {
            "id": 16000086,
            "name": "SHADE",
            "power": 10,
            "trophies": 8
          }
        },
        "teams": [
          [
            {
              "tag": "#2GLCCYGC9V",
              "name": "SuperSurge",
              "brawler": {
                "id": 16000007,
                "name": "JESSIE",
                "power": 1,
                "trophies": 3
              }
            },
            {
              "tag": "#2GL8YLVPGY",
              "name": "fettuccine",
              "brawler": {
                "id": 16000010,
                "name": "EL PRIMO",
                "power": 1,
                "trophies": 0
              }
            },
            {
              "tag": "#CJU28JQC",
              "name": "lil cuzzo",
              "brawler": {
                "id": 16000086,
                "name": "SHADE",
                "power": 10,
                "trophies": 8
              }
            }
          ],
          [
            {
              "tag": "#P08U2CP0C",
              "name": "\u26e9|Rzm64\ud83c\udf8b",
              "brawler": {
                "id": 16000006,
                "name": "BARLEY",
                "power": 5,
                "trophies": 16
              }
            },
            {
              "tag": "#P09RY9JYV",
              "name": "adekyoutuberyt",
              "brawler": {
                "id": 16000010,
                "name": "EL PRIMO",
                "power": 4,
                "trophies": 8
              }
            },
            {
              "tag": "#P02VGP2YR",
              "name": "picolo",
              "brawler": {
                "id": 16000007,
                "name": "JESSIE",
                "power": 5,
                "trophies": 16
              }
            }
          ]
        ]
      }
    }
  ],
  "paging": {
    "cursors": {}
  }
}