{
  "items": [
    {
      "battleTime": "20250505T213945.000Z",
      "event": {
        "id": 15001026,
        "mode": "gemGrab",
        "map": "On a Roll"
      },
      "battle": {
        "mode": "gemGrab",
        "type": "ranked",
        "result": "defeat",
        "duration": 98,
        "trophyChange": -7,
        "starPlayer": {
          "tag": "#Y2G02VV92",
          "name": "progamer954 yt",
          "brawler": {
            "id": 16000083,
            "name": "CLANCY",
            "power": 11,
            "trophies": 947
          }
        },
        "teams": [
          [
            {
              "tag": "#Y2G02VV92",
              "name": "progamer954 yt",
              "brawler": {
                "id": 16000083,
                "name": "CLANCY",
                "power": 11,
                "trophies": 947
              }
            },
            {
              "tag": "#YRLVRLQQL",
              "name": "Cat421",
              "brawler": {
                "id": 16000017,
                "name": "TARA",
                "power": 11,
                "trophies": 979
              }
            },
            {
              "tag": "#2RV8QQQ2",
              "name": "Yummytoes",
              "brawler": {
                "id": 16000015,
                "name": "PIPER",
                "power": 11,
                "trophies": 945
              }
            }
          ],
          [
            {
              "tag": "#P0CL8GCVJ",
              "name": "Brawler",
              "brawler": {
                "id": 16000081,
                "name": "LILY",
                "power": 11,
                "trophies": 963
              }
            },
            {
              "tag": "#9C92U8890",
              "name": "Delta",
              "brawler": {
                "id": 16000021,
                "name": "GENE",
                "power": 11,
                "trophies": 957
              }
            },
            {
              "tag": "#2LV0PLP8G",
              "name": "connorli",
              "brawler": {
                "id": 16000001,
                "name": "COLT",
                "power": 11,
                "trophies": 969
              }
            }
          ]
        ]
      }
    },
    {
      "battleTime": "20250505T181634.000Z",
      "event": {
        "id": 15001026,
        "mode": "gemGrab",
        "map": "On a Roll"
      },
      "battle": {
        "mode": "gemGrab",
        "type": "ranked",
        "result": "defeat",
        "duration": 128,
        "trophyChange": -7,
        "starPlayer": {
          "tag": "#UVPU0Q9P",
          "name": "cp",
          "brawler": {
            "id": 16000085,
            "name": "KENJI",
            "power": 11,
            "trophies": 934
          }
        },
        "teams": [
          [
            {
              "tag": "#Y8YLPL8GY",
              "name": "AndreA",
              "brawler": {
                "id": 16000049,
                "name": "BUZZ",
                "power": 11,
                "trophies": 879
              }
            },
            {
              "tag": "#YPVV8Y0UL",
              "name": "\u2744L133Y\u2744",
              "brawler": {
                "id": 16000039,
                "name": "COLETTE",
                "power": 11,
                "trophies": 960
              }
            },
            {
              "tag": "#2LV0PLP8G",
              "name": "connorli",
              "brawler": {
                "id": 16000001,
                "name": "COLT",
                "power": 11,
                "trophies": 976
              }
            }
          ],
          [
            {
              "tag": "#G88CGV8JL",
              "name": "el momero87",
              "brawler": {
                "id": 16000018,
                "name": "DARRYL",
                "power": 11,
                "trophies": 956
              }
            },
            {
              "tag": "#UVPU0Q9P",
              "name": "cp",
              "brawler": {
                "id": 16000085,
                "name": "KENJI",
                "power": 11,
                "trophies": 934
              }
            },
            {
              "tag": "#9L2982RG2",
              "name": "paola. 0026",
              "brawler": {
                "id": 16000043,
                "name": "EDGAR",
                "power": 11,
                "trophies": 928
              }
            }
          ]
        ]
      }
    },
    {
      "battleTime": "20250505T155328.000Z",
      "event": {
        "id": 15001026,
        "mode": "gemGrab",
        "map": "On a Roll"
      },
      "battle": {
        "mode": "gemGrab",
        "type": "ranked",
        "result": "defeat",
        "duration": 97,
        "trophyChange": -7,
        "starPlayer": {
          "tag": "#8CY99JLVL",
          "name": "Rey",
          "brawler": {
            "id": 16000085,
            "name": "KENJI",
            "power": 11,
            "trophies": 985
          }
        },
        "teams": [
          [
            {
              "tag": "#2QG28LG90",
              "name": "brando416",
              "brawler": {
                "id": 16000012,
                "name": "CROW",
                "power": 11,
                "trophies": 991
              }
            },
            {
              "tag": "#2LV0PLP8G",
              "name": "connorli",
              "brawler": {
                "id": 16000001,
                "name": "COLT",
                "power": 11,
                "trophies": 983
              }
            },
            {
              "tag": "#229L2VC9",
              "name": "Existable",
              "brawler": {
                "id": 16000085,
                "name": "KENJI",
                "power": 11,
                "trophies": 978
              }
            }
          ],
          [
            {
              "tag": "#LGQGY8RCU",
              "name": "Chris",
              "brawler": {
                "id": 16000045,
                "name": "STU",
                "power": 11,
                "trophies": 995
              }
            },
            {
              "tag": "#UC0VU82PR",
              "name": "I AM",
              "brawler": {
                "id": 16000017,
                "name": "TARA",
                "power": 11,
                "trophies": 986
              }
            },
            {
              "tag": "#8CY99JLVL",
              "name": "Rey",
              "brawler": {
                "id": 16000085,
                "name": "KENJI",
                "power": 11,
                "trophies": 985
              }
            }
          ]
        ]
      }
    },
    {
      "battleTime": "20250505T145538.000Z",
      "event": {
        "id": 15001026,
        "mode": "gemGrab",
        "map": "On a Roll"
      },
      "battle": {
        "mode": "gemGrab",
        "type": "ranked",
        "result": "defeat",
        "duration": 136,
        "trophyChange": -7,
        "starPlayer": {
          "tag": "#2QGQY8L2L",
          "name": "jaysav",
          "brawler": {
            "id": 16000092,
            "name": "FINX",
            "power": 11,
            "trophies": 426
          }
        },
        "teams": [
          [
            {
              "tag": "#2QJ8JJQ2Q9",
              "name": "MylaBoo",
              "brawler": {
                "id": 16000029,
                "name": "BEA",
                "power": 11,
                "trophies": 958
              }
            },
            {
              "tag": "#2QGQY8L2L",
              "name": "jaysav",
              "brawler": {
                "id": 16000092,
                "name": "FINX",
                "power": 11,
                "trophies": 426
              }
            },
            {
              "tag": "#CJ8RJU92V",
              "name": "pepexs\ud83e\udd2b\ud83e\uddcf\u200d\u2642\ufe0f",
              "brawler": {
                "id": 16000026,
                "name": "BIBI",
                "power": 11,
                "trophies": 943
              }
            }
          ],
          [
            {
              "tag": "#2LLLJPLPU",
              "name": "AutisticMonke",
              "brawler": {
                "id": 16000083,
                "name": "CLANCY",
                "power": 11,
                "trophies": 980
              }
            },
            {
              "tag": "#2LV0PLP8G",
              "name": "connorli",
              "brawler": {
                "id": 16000001,
                "name": "COLT",
                "power": 11,
                "trophies": 990
              }
            },
            {
              "tag": "#29R0J2R20",
              "name": "doritos roboct",
              "brawler": {
                "id": 16000085,
                "name": "KENJI",
                "power": 11,
                "trophies": 992
              }
            }
          ]
        ]
      }
    },
    {
      "battleTime": "20250505T145248.000Z",
      "event": {
        "id": 15001026,
        "mode": "gemGrab",
        "map": "On a Roll"
      },
      "battle": {
        "mode": "gemGrab",
        "type": "ranked",
        "result": "victory",
        "duration": 158,
        "trophyChange": 9,
        "starPlayer": {
          "tag": "#2LV0PLP8G",
          "name": "connorli",
          "brawler": {
            "id": 16000001,
            "name": "COLT",
            "power": 11,
            "trophies": 981
          }
        },
        "teams": [
          [
            {
              "tag": "#JCUJUQ90",
              "name": "joshy",
              "brawler": {
                "id": 16000046,
                "name": "BELLE",
                "power": 11,
                "trophies": 996
              }
            },
            {
              "tag": "#2PJLL9QQ8",
              "name": "Rino pistolas",
              "brawler": {
                "id": 16000045,
                "name": "STU",
                "power": 11,
                "trophies": 980
              }
            },
            {
              "tag": "#GCCRG98UJ",
              "name": "T0mikz",
              "brawler": {
                "id": 16000010,
                "name": "EL PRIMO",
                "power": 11,
                "trophies": 992
              }
            }
          ],
          [
            {
              "tag": "#Y80Y0CPV0",
              "name": "Big Jim \ud83e\udd2b\ud83e\uddcf\ud83c\udfff",
              "brawler": {
                "id": 16000045,
                "name": "STU",
                "power": 11,
                "trophies": 981
              }
            },
            {
              "tag": "#2Q0G2GCJ80",
              "name": "\ud83d\udc79the killer\ud83d\udc79",
              "brawler": {
                "id": 16000011,
                "name": "MORTIS",
                "power": 11,
                "trophies": 989
              }
            },
            {
              "tag": "#2LV0PLP8G",
              "name": "connorli",
              "brawler": {
                "id": 16000001,
                "name": "COLT",
                "power": 11,
                "trophies": 981
              }
            }
          ]
        ]
      }
    },
    {
      "battleTime": "20250505T144941.000Z",
      "event": {
        "id": 15001026,
        "mode": "gemGrab",
        "map": "On a Roll"
      },
      "battle": {
        "mode": "gemGrab",
        "type": "ranked",
        "result": "victory",
        "duration": 93,
        "trophyChange": 8,
        "starPlayer": {
          "tag": "#2LV0PLP8G",
          "name": "connorli",
          "brawler": {
            "id": 16000001,
            "name": "COLT",
            "power": 11,
            "trophies": 973
          }
        },
        "teams": [
          [
            {
              "tag": "#R0YV908VV",
              "name": "\ud83e\udd47\ud83c\uddf5\u200a\ud83c\uddea\u200a\ud83c\uddf5\u200a\ud83c\uddea\ud83e\udd47",
              "brawler": {
                "id": 16000049,
                "name": "BUZZ",
                "power": 11,
                "trophies": 981
              }
            },
            {
              "tag": "#GVQ9UCQ8P",
              "name": "Ippo\ud83e\udd4a",
              "brawler": {
                "id": 16000070,
                "name": "CORDELIUS",
                "power": 11,
                "trophies": 968
              }
            },
            {
              "tag": "#LG2VQCYPC",
              "name": "Ladybug",
              "brawler": {
                "id": 16000014,
                "name": "BO",
                "power": 11,
                "trophies": 966
              }
            }
          ],
          [
            {
              "tag": "#2LV0PLP8G",
              "name": "connorli",
              "brawler": {
                "id": 16000001,
                "name": "COLT",
                "power": 11,
                "trophies": 973
              }
            },
            {
              "tag": "#222GYQR0P",
              "name": "\u26a1LSD_CARLITOX\u26a1",
              "brawler": {
                "id": 16000038,
                "name": "SURGE",
                "power": 11,
                "trophies": 974
              }
            },
            {
              "tag": "#JCUJUQ90",
              "name": "joshy",
              "brawler": {
                "id": 16000046,
                "name": "BELLE",
                "power": 11,
                "trophies": 988
              }
            }
          ]
        ]
      }
    },
    {
      "battleTime": "20250505T144733.000Z",
      "event": {
        "id": 15001026,
        "mode": "gemGrab",
        "map": "On a Roll"
      },
      "battle": {
        "mode": "gemGrab",
        "type": "ranked",
        "result": "defeat",
        "duration": 118,
        "trophyChange": -7,
        "starPlayer": {
          "tag": "#GJYPUGQQU",
          "name": "cristianlm05xd",
          "brawler": {
            "id": 16000063,
            "name": "CHESTER",
            "power": 11,
            "trophies": 996
          }
        },
        "teams": [
          [
            {
              "tag": "#2P00PUYYL",
              "name": "Blackbird",
              "brawler": {
                "id": 16000081,
                "name": "LILY",
                "power": 11,
                "trophies": 973
              }
            },
            {
              "tag": "#2LV0PLP8G",
              "name": "connorli",
              "brawler": {
                "id": 16000001,
                "name": "COLT",
                "power": 11,
                "trophies": 980
              }
            },
            {
              "tag": "#9C9PCR2LG",
              "name": "BASSITO",
              "brawler": {
                "id": 16000017,
                "name": "TARA",
                "power": 11,
                "trophies": 992
              }
            }
          ],
          [
            {
              "tag": "#RL92RG2QP",
              "name": "AB saleh",
              "brawler": {
                "id": 16000045,
                "name": "STU",
                "power": 11,
                "trophies": 805
              }
            },
            {
              "tag": "#8VP9G2CL0",
              "name": "equalizator",
              "brawler": {
                "id": 16000032,
                "name": "MAX",
                "power": 11,
                "trophies": 994
              }
            },
            {
              "tag": "#GJYPUGQQU",
              "name": "cristianlm05xd",
              "brawler": {
                "id": 16000063,
                "name": "CHESTER",
                "power": 11,
                "trophies": 996
              }
            }
          ]
        ]
      }
    },
    {
      "battleTime": "20250505T130110.000Z",
      "event": {
        "id": 15001026,
        "mode": "gemGrab",
        "map": "On a Roll"
      },
      "battle": {
        "mode": "gemGrab",
        "type": "ranked",
        "result": "victory",
        "duration": 208,
        "trophyChange": 8,
        "starPlayer": {
          "tag": "#C09LPL28",
          "name": "\u26a1castro17\u26a1",
          "brawler": {
            "id": 16000030,
            "name": "EMZ",
            "power": 11,
            "trophies": 962
          }
        },
        "teams": [
          [
            {
              "tag": "#2J2GUL89L",
              "name": "Robo",
              "brawler": {
                "id": 16000085,
                "name": "KENJI",
                "power": 11,
                "trophies": 948
              }
            },
            {
              "tag": "#LPRV02QQP",
              "name": "AcxeL \u1d9c\u1d50 \u8a87",
              "brawler": {
                "id": 16000036,
                "name": "NANI",
                "power": 11,
                "trophies": 945
              }
            },
            {
              "tag": "#999G2RRG2",
              "name": "Eevee",
              "brawler": {
                "id": 16000054,
                "name": "FANG",
                "power": 11,
                "trophies": 951
              }
            }
          ],
          [
            {
              "tag": "#C09LPL28",
              "name": "\u26a1castro17\u26a1",
              "brawler": {
                "id": 16000030,
                "name": "EMZ",
                "power": 11,
                "trophies": 962
              }
            },
            {
              "tag": "#2LV0PLP8G",
              "name": "connorli",
              "brawler": {
                "id": 16000001,
                "name": "COLT",
                "power": 11,
                "trophies": 972
              }
            },
            {
              "tag": "#98C2PUPR",
              "name": "laxuslayer",
              "brawler": {
                "id": 16000022,
                "name": "TICK",
                "power": 11,
                "trophies": 904
              }
            }
          ]
        ]
      }
    },
    {
      "battleTime": "20250505T125251.000Z",
      "event": {
        "id": 15001026,
        "mode": "gemGrab",
        "map": "On a Roll"
      },
      "battle": {
        "mode": "gemGrab",
        "type": "ranked",
        "result": "defeat",
        "duration": 99,
        "trophyChange": -7,
        "starPlayer": {
          "tag": "#2LRC2GGYP",
          "name": "TW|rey",
          "brawler": {
            "id": 16000085,
            "name": "KENJI",
            "power": 11,
            "trophies": 636
          }
        },
        "teams": [
          [
            {
              "tag": "#2LRC2GGYP",
              "name": "TW|rey",
              "brawler": {
                "id": 16000085,
                "name": "KENJI",
                "power": 11,
                "trophies": 636
              }
            },
            {
              "tag": "#88RRL2CGQ",
              "name": "TW|CHAVEZ",
              "brawler": {
                "id": 16000048,
                "name": "GROM",
                "power": 11,
                "trophies": 988
              }
            },
            {
              "tag": "#GG9YJQRQU",
              "name": "UnPanBv",
              "brawler": {
                "id": 16000012,
                "name": "CROW",
                "power": 11,
                "trophies": 969
              }
            }
          ],
          [
            {
              "tag": "#2LV0PLP8G",
              "name": "connorli",
              "brawler": {
                "id": 16000001,
                "name": "COLT",
                "power": 11,
                "trophies": 979
              }
            },
            {
              "tag": "#8PPPLCRL",
              "name": "AFK cus iEating",
              "brawler": {
                "id": 16000023,
                "name": "LEON",
                "power": 11,
                "trophies": 982
              }
            },
            {
              "tag": "#PQJQRUQV",
              "name": "x_x",
              "brawler": {
                "id": 16000085,
                "name": "KENJI",
                "power": 11,
                "trophies": 978
              }
            }
          ]
        ]
      }
    },
    {
      "battleTime": "20250505T030815.000Z",
      "event": {
        "id": 15001026,
        "mode": "gemGrab",
        "map": "On a Roll"
      },
      "battle": {
        "mode": "gemGrab",
        "type": "ranked",
        "result": "defeat",
        "duration": 134,
        "trophyChange": -7,
        "starPlayer": {
          "tag": "#GJ8QRP0",
          "name": "\u1d31\u1d38\u1d40 |FerLemus\u2122",
          "brawler": {
            "id": 16000042,
            "name": "BYRON",
            "power": 11,
            "trophies": 978
          }
        },
        "teams": [
          [
            {
              "tag": "#YCUG0LJJU",
              "name": "MrFries",
              "brawler": {
                "id": 16000040,
                "name": "AMBER",
                "power": 10,
                "trophies": 850
              }
            },
            {
              "tag": "#222VPRP8Y",
              "name": "VIRUS",
              "brawler": {
                "id": 16000069,
                "name": "HANK",
                "power": 11,
                "trophies": 987
              }
            },
            {
              "tag": "#GQ9JLUY9G",
              "name": "YulTheWizard",
              "brawler": {
                "id": 16000042,
                "name": "BYRON",
                "power": 10,
                "trophies": 947
              }
            }
          ],
          [
            {
              "tag": "#2LV0PLP8G",
              "name": "connorli",
              "brawler": {
                "id": 16000001,
                "name": "COLT",
                "power": 11,
                "trophies": 986
              }
            },
            {
              "tag": "#GJ8QRP0",
              "name": "\u1d31\u1d38\u1d40 |FerLemus\u2122",
              "brawler": {
                "id": 16000042,
                "name": "BYRON",
                "power": 11,
                "trophies": 978
              }
            },
            {
              "tag": "#UJ0YUGGR",
              "name": "Ete Sech",
              "brawler": {
                "id": 16000023,
                "name": "LEON",
                "power": 11,
                "trophies": 969
              }
            }
          ]
        ]
      }
    },
    {
      "battleTime": "20250505T030338.000Z",
      "event": {
        "id": 15001026,
        "mode": "gemGrab",
        "map": "On a Roll"
      },
      "battle": {
        "mode": "gemGrab",
        "type": "ranked",
        "result": "victory",
        "duration": 124,
        "trophyChange": 9,
        "starPlayer": {
          "tag": "#LRYCCPG0U",
          "name": "RealHomieG88",
          "brawler": {
            "id": 16000042,
            "name": "BYRON",
            "power": 10,
            "trophies": 979
          }
        },
        "teams": [
          [
            {
              "tag": "#2QRGGV2Y90",
              "name": "\u8881\u822a",
              "brawler": {
                "id": 16000069,
                "name": "HANK",
                "power": 9,
                "trophies": 939
              }
            },
            {
              "tag": "#LRYCCPG0U",
              "name": "RealHomieG88",
              "brawler": {
                "id": 16000042,
                "name": "BYRON",
                "power": 10,
                "trophies": 979
              }
            },
            {
              "tag": "#2LV0PLP8G",
              "name": "connorli",
              "brawler": {
                "id": 16000001,
                "name": "COLT",
                "power": 11,
                "trophies": 977
              }
            }
          ],
          [
            {
              "tag": "#Y0V9LVQ8V",
              "name": "yoJeiker",
              "brawler": {
                "id": 16000040,
                "name": "AMBER",
                "power": 11,
                "trophies": 993
              }
            },
            {
              "tag": "#299QUCV0L",
              "name": "\ua9c1\u0f12\u262c\ud835\udce3\ud835\udcf2\ud835\udcf61\ud835\udd03\ud835\udd03",
              "brawler": {
                "id": 16000081,
                "name": "LILY",
                "power": 11,
                "trophies": 992
              }
            },
            {
              "tag": "#29P0L2UPG",
              "name": "CROW\ud83d\udd25",
              "brawler": {
                "id": 16000044,
                "name": "RUFFS",
                "power": 11,
                "trophies": 992
              }
            }
          ]
        ]
      }
    },
    {
      "battleTime": "20250504T192126.000Z",
      "event": {
        "id": 15000008,
        "mode": "gemGrab",
        "map": "Crystal Arcade"
      },
      "battle": {
        "mode": "gemGrab",
        "type": "ranked",
        "result": "victory",
        "duration": 79,
        "trophyChange": 8,
        "starPlayer": {
          "tag": "#U8RJYPLC",
          "name": "ShadowLegacy37",
          "brawler": {
            "id": 16000085,
            "name": "KENJI",
            "power": 11,
            "trophies": 964
          }
        },
        "teams": [
          [
            {
              "tag": "#JQQGVCQVY",
              "name": "tiny-dragon",
              "brawler": {
                "id": 16000038,
                "name": "SURGE",
                "power": 11,
                "trophies": 975
              }
            },
            {
              "tag": "#2LV0PLP8G",
              "name": "connorli",
              "brawler": {
                "id": 16000001,
                "name": "COLT",
                "power": 11,
                "trophies": 969
              }
            },
            {
              "tag": "#U8RJYPLC",
              "name": "ShadowLegacy37",
              "brawler": {
                "id": 16000085,
                "name": "KENJI",
                "power": 11,
                "trophies": 964
              }
            }
          ],
          [
            {
              "tag": "#29RRRJL28",
              "name": "andrescr.exe.",
              "brawler": {
                "id": 16000092,
                "name": "FINX",
                "power": 7,
                "trophies": 122
              }
            },
            {
              "tag": "#22VP2QLQRG",
              "name": "sofi",
              "brawler": {
                "id": 16000022,
                "name": "TICK",
                "power": 11,
                "trophies": 909
              }
            },
            {
              "tag": "#C98CGJ9Q8",
              "name": "RGB/GOKU",
              "brawler": {
                "id": 16000023,
                "name": "LEON",
                "power": 11,
                "trophies": 941
              }
            }
          ]
        ]
      }
    },
    {
      "battleTime": "20250504T163006.000Z",
      "event": {
        "id": 15000008,
        "mode": "gemGrab",
        "map": "Crystal Arcade"
      },
      "battle": {
        "mode": "gemGrab",
        "type": "ranked",
        "result": "defeat",
        "duration": 132,
        "trophyChange": -7,
        "starPlayer": {
          "tag": "#UVLGCCUJ",
          "name": "yisus1601",
          "brawler": {
            "id": 16000079,
            "name": "ANGELO",
            "power": 11,
            "trophies": 991
          }
        },
        "teams": [
          [
            {
              "tag": "#UVLGCCUJ",
              "name": "yisus1601",
              "brawler": {
                "id": 16000079,
                "name": "ANGELO",
                "power": 11,
                "trophies": 991
              }
            },
            {
              "tag": "#2LYL9U2JPC",
              "name": "ALFRED18",
              "brawler": {
                "id": 16000063,
                "name": "CHESTER",
                "power": 11,
                "trophies": 985
              }
            },
            {
              "tag": "#88VUVPVCV",
              "name": "Bladez",
              "brawler": {
                "id": 16000085,
                "name": "KENJI",
                "power": 11,
                "trophies": 975
              }
            }
          ],
          [
            {
              "tag": "#2LV0PLP8G",
              "name": "connorli",
              "brawler": {
                "id": 16000001,
                "name": "COLT",
                "power": 11,
                "trophies": 976
              }
            },
            {
              "tag": "#9JUQYR2LU",
              "name": "Santy_S)",
              "brawler": {
                "id": 16000085,
                "name": "KENJI",
                "power": 11,
                "trophies": 985
              }
            },
            {
              "tag": "#QGJ8Y2YY",
              "name": "\ud835\udc0a\ud835\udd40\u2124\u2124",
              "brawler": {
                "id": 16000081,
                "name": "LILY",
                "power": 11,
                "trophies": 992
              }
            }
          ]
        ]
      }
    },
    {
      "battleTime": "20250504T154003.000Z",
      "event": {
        "id": 15000008,
        "mode": "gemGrab",
        "map": "Crystal Arcade"
      },
      "battle": {
        "mode": "gemGrab",
        "type": "ranked",
        "result": "defeat",
        "duration": 99,
        "trophyChange": -7,
        "starPlayer": {
          "tag": "#CYPVQLQQ",
          "name": "WyDek",
          "brawler": {
            "id": 16000023,
            "name": "LEON",
            "power": 11,
            "trophies": 989
          }
        },
        "teams": [
          [
            {
              "tag": "#2LV0PLP8G",
              "name": "connorli",
              "brawler": {
                "id": 16000001,
                "name": "COLT",
                "power": 11,
                "trophies": 983
              }
            },
            {
              "tag": "#8YJURYRGG",
              "name": "T\u263a\ufe0e\ufe0eF|[\ud835\udc1a\ud835\udc2c]|\u263b\ufe0e",
              "brawler": {
                "id": 16000023,
                "name": "LEON",
                "power": 11,
                "trophies": 992
              }
            },
            {
              "tag": "#2L9JV98QVY",
              "name": "Crabster",
              "brawler": {
                "id": 16000085,
                "name": "KENJI",
                "power": 11,
                "trophies": 992
              }
            }
          ],
          [
            {
              "tag": "#99LURG09R",
              "name": "MysteryBox48",
              "brawler": {
                "id": 16000022,
                "name": "TICK",
                "power": 11,
                "trophies": 992
              }
            },
            {
              "tag": "#CYPVQLQQ",
              "name": "WyDek",
              "brawler": {
                "id": 16000023,
                "name": "LEON",
                "power": 11,
                "trophies": 989
              }
            },
            {
              "tag": "#RC9U9U2Q",
              "name": "chasseurdeprime",
              "brawler": {
                "id": 16000010,
                "name": "EL PRIMO",
                "power": 11,
                "trophies": 990
              }
            }
          ]
        ]
      }
    },
    {
      "battleTime": "20250504T153756.000Z",
      "event": {
        "id": 15000008,
        "mode": "gemGrab",
        "map": "Crystal Arcade"
      },
      "battle": {
        "mode": "gemGrab",
        "type": "ranked",
        "result": "victory",
        "duration": 127,
        "trophyChange": 8,
        "starPlayer": {
          "tag": "#9V99928VC",
          "name": "Oswaldo",
          "brawler": {
            "id": 16000010,
            "name": "EL PRIMO",
            "power": 10,
            "trophies": 951
          }
        },
        "teams": [
          [
            {
              "tag": "#9822JGC8C",
              "name": "QLS | Anyel.070",
              "brawler": {
                "id": 16000040,
                "name": "AMBER",
                "power": 11,
                "trophies": 968
              }
            },
            {
              "tag": "#2LV0PLP8G",
              "name": "connorli",
              "brawler": {
                "id": 16000001,
                "name": "COLT",
                "power": 11,
                "trophies": 975
              }
            },
            {
              "tag": "#9V99928VC",
              "name": "Oswaldo",
              "brawler": {
                "id": 16000010,
                "name": "EL PRIMO",
                "power": 10,
                "trophies": 951
              }
            }
          ],
          [
            {
              "tag": "#8V29VRGJ",
              "name": "XxParkaxX",
              "brawler": {
                "id": 16000029,
                "name": "BEA",
                "power": 11,
                "trophies": 992
              }
            },
            {
              "tag": "#2C98Y9C9Q",
              "name": "BR|\u9ed1\u8272\u7684\u2661\u271d\ufe0fR",
              "brawler": {
                "id": 16000010,
                "name": "EL PRIMO",
                "power": 11,
                "trophies": 989
              }
            },
            {
              "tag": "#Q8UR88RV2",
              "name": "jose",
              "brawler": {
                "id": 16000043,
                "name": "EDGAR",
                "power": 11,
                "trophies": 992
              }
            }
          ]
        ]
      }
    },
    {
      "battleTime": "20250504T143334.000Z",
      "event": {
        "id": 15000974,
        "mode": "wipeout5V5",
        "map": "Courtyard Clashers"
      },
      "battle": {
        "mode": "wipeout",
        "type": "ranked",
        "result": "draw",
        "duration": 180,
        "starPlayer": {
          "tag": "#GU0RCG9Q8",
          "name": "SNAKE",
          "brawler": {
            "id": 16000048,
            "name": "GROM",
            "power": 11,
            "trophies": 982
          }
        },
        "teams": [
          [
            {
              "tag": "#L2CYGCQUC",
              "name": "\u2728PINK.AURA\u2728",
              "brawler": {
                "id": 16000065,
                "name": "MANDY",
                "power": 11,
                "trophies": 971
              }
            },
            {
              "tag": "#QPYL0CL2P",
              "name": "Mr.pollo\ud83d\udc25",
              "brawler": {
                "id": 16000031,
                "name": "MR. P",
                "power": 11,
                "trophies": 981
              }
            },
            {
              "tag": "#GU0RCG9Q8",
              "name": "SNAKE",
              "brawler": {
                "id": 16000048,
                "name": "GROM",
                "power": 11,
                "trophies": 982
              }
            },
            {
              "tag": "#9UCGVRJQG",
              "name": "Big Dom",
              "brawler": {
                "id": 16000022,
                "name": "TICK",
                "power": 11,
                "trophies": 982
              }
            },
            {
              "tag": "#2LV0PLP8G",
              "name": "connorli",
              "brawler": {
                "id": 16000001,
                "name": "COLT",
                "power": 11,
                "trophies": 975
              }
            }
          ],
          [
            {
              "tag": "#LPGGL8U",
              "name": "Root\ud83e\uded6",
              "brawler": {
                "id": 16000015,
                "name": "PIPER",
                "power": 11,
                "trophies": 992
              }
            },
            {
              "tag": "#2GQC89QGU0",
              "name": "Brawlstarmonkey",
              "brawler": {
                "id": 16000005,
                "name": "SPIKE",
                "power": 11,
                "trophies": 994
              }
            },
            {
              "tag": "#2Q2CC2UVRQ",
              "name": "Abaha",
              "brawler": {
                "id": 16000065,
                "name": "MANDY",
                "power": 11,
                "trophies": 992
              }
            },
            {
              "tag": "#2QPVC9Y98V",
              "name": "oj",
              "brawler": {
                "id": 16000007,
                "name": "JESSIE",
                "power": 11,
                "trophies": 992
              }
            },
            {
              "tag": "#GJVQQCYR2",
              "name": "aldebaran",
              "brawler": {
                "id": 16000003,
                "name": "BROCK",
                "power": 11,
                "trophies": 886
              }
            }
          ]
        ]
      }
    },
    {
      "battleTime": "20250504T042540.000Z",
      "event": {
        "id": 15000700,
        "mode": "knockout5V5",
        "map": "Sizzling Chambers"
      },
      "battle": {
        "mode": "knockout",
        "type": "ranked",
        "result": "defeat",
        "duration": 112,
        "trophyChange": -7,
        "starPlayer": {
          "tag": "#YCVLV98JJ",
          "name": "OT |PrImE-XaMpL",
          "brawler": {
            "id": 16000010,
            "name": "EL PRIMO",
            "power": 10,
            "trophies": 651
          }
        },
        "teams": [
          [
            {
              "tag": "#288YJGCR",
              "name": "Chaayy1",
              "brawler": {
                "id": 16000014,
                "name": "BO",
                "power": 11,
                "trophies": 986
              }
            },
            {
              "tag": "#RVCQGJY",
              "name": "Esnupi",
              "brawler": {
                "id": 16000004,
                "name": "RICO",
                "power": 11,
                "trophies": 719
              }
            },
            {
              "tag": "#220JYYRRR2",
              "name": "D A S\ud83d\udda4",
              "brawler": {
                "id": 16000043,
                "name": "EDGAR",
                "power": 11,
                "trophies": 987
              }
            },
            {
              "tag": "#9P2ULL0JY",
              "name": "Prince0Fva",
              "brawler": {
                "id": 16000022,
                "name": "TICK",
                "power": 11,
                "trophies": 993
              }
            },
            {
              "tag": "#2LV0PLP8G",
              "name": "connorli",
              "brawler": {
                "id": 16000001,
                "name": "COLT",
                "power": 11,
                "trophies": 982
              }
            }
          ],
          [
            {
              "tag": "#Y0RC28QYJ",
              "name": "Pixel",
              "brawler": {
                "id": 16000026,
                "name": "BIBI",
                "power": 9,
                "trophies": 874
              }
            },
            {
              "tag": "#YCVLV98JJ",
              "name": "OT |PrImE-XaMpL",
              "brawler": {
                "id": 16000010,
                "name": "EL PRIMO",
                "power": 10,
                "trophies": 651
              }
            },
            {
              "tag": "#28C99JU29",
              "name": "BB|Dark",
              "brawler": {
                "id": 16000001,
                "name": "COLT",
                "power": 11,
                "trophies": 972
              }
            },
            {
              "tag": "#QLPGY2CU",
              "name": "BuddySmokes",
              "brawler": {
                "id": 16000079,
                "name": "ANGELO",
                "power": 11,
                "trophies": 730
              }
            },
            {
              "tag": "#8CJPC0LV",
              "name": "Troy",
              "brawler": {
                "id": 16000057,
                "name": "JANET",
                "power": 11,
                "trophies": 974
              }
            }
          ]
        ]
      }
    },
    {
      "battleTime": "20250504T042300.000Z",
      "event": {
        "id": 15000700,
        "mode": "knockout5V5",
        "map": "Sizzling Chambers"
      },
      "battle": {
        "mode": "knockout",
        "type": "ranked",
        "result": "victory",
        "duration": 265,
        "trophyChange": 9,
        "starPlayer": {
          "tag": "#2URQCCQUJ",
          "name": "Rich21",
          "brawler": {
            "id": 16000005,
            "name": "SPIKE",
            "power": 11,
            "trophies": 980
          }
        },
        "teams": [
          [
            {
              "tag": "#9UP92JCVR",
              "name": "ss_tts789",
              "brawler": {
                "id": 16000042,
                "name": "BYRON",
                "power": 11,
                "trophies": 241
              }
            },
            {
              "tag": "#22R0YPVV",
              "name": "iiiiii",
              "brawler": {
                "id": 16000043,
                "name": "EDGAR",
                "power": 11,
                "trophies": 948
              }
            },
            {
              "tag": "#2U0RPV82G",
              "name": "panda\ud83d\udc3c\ud83d\udc3e",
              "brawler": {
                "id": 16000001,
                "name": "COLT",
                "power": 11,
                "trophies": 967
              }
            },
            {
              "tag": "#Y9G0G0QUY",
              "name": "BsC|Jav",
              "brawler": {
                "id": 16000052,
                "name": "MEG",
                "power": 9,
                "trophies": 524
              }
            },
            {
              "tag": "#JP90PY2U0",
              "name": "Paimon",
              "brawler": {
                "id": 16000065,
                "name": "MANDY",
                "power": 11,
                "trophies": 939
              }
            }
          ],
          [
            {
              "tag": "#UJ8LQVGP",
              "name": "TorisBoyfriend",
              "brawler": {
                "id": 16000003,
                "name": "BROCK",
                "power": 11,
                "trophies": 963
              }
            },
            {
              "tag": "#2QC0UC8Y2J",
              "name": "el gragon",
              "brawler": {
                "id": 16000043,
                "name": "EDGAR",
                "power": 11,
                "trophies": 972
              }
            },
            {
              "tag": "#2QJPQ9LQ2C",
              "name": "Violet",
              "brawler": {
                "id": 16000065,
                "name": "MANDY",
                "power": 11,
                "trophies": 996
              }
            },
            {
              "tag": "#2URQCCQUJ",
              "name": "Rich21",
              "brawler": {
                "id": 16000005,
                "name": "SPIKE",
                "power": 11,
                "trophies": 980
              }
            },
            {
              "tag": "#2LV0PLP8G",
              "name": "connorli",
              "brawler": {
                "id": 16000001,
                "name": "COLT",
                "power": 11,
                "trophies": 973
              }
            }
          ]
        ]
      }
    },
    {
      "battleTime": "20250504T041756.000Z",
      "event": {
        "id": 15000700,
        "mode": "knockout5V5",
        "map": "Sizzling Chambers"
      },
      "battle": {
        "mode": "knockout",
        "type": "ranked",
        "result": "victory",
        "duration": 130,
        "trophyChange": 8,
        "starPlayer": {
          "tag": "#P88L8PPPL",
          "name": "YT]@$SWEAT@$",
          "brawler": {
            "id": 16000004,
            "name": "RICO",
            "power": 11,
            "trophies": 969
          }
        },
        "teams": [
          [
            {
              "tag": "#282LYJ0LQQ",
              "name": "Gerson",
              "brawler": {
                "id": 16000003,
                "name": "BROCK",
                "power": 9,
                "trophies": 384
              }
            },
            {
              "tag": "#2LU88Q0VQ0",
              "name": "Tati\ud83d\udc51",
              "brawler": {
                "id": 16000017,
                "name": "TARA",
                "power": 11,
                "trophies": 951
              }
            },
            {
              "tag": "#2YGCJVP8Q2",
              "name": "Chinito\ud83d\udc51",
              "brawler": {
                "id": 16000043,
                "name": "EDGAR",
                "power": 11,
                "trophies": 987
              }
            },
            {
              "tag": "#GGC9C8PRG",
              "name": "\uff27\uff2f \u4e97 \uff29\uff2e\uff33\uff21\uff2e\uff2f\u00d7\u035c\u135d\u059f",
              "brawler": {
                "id": 16000054,
                "name": "FANG",
                "power": 11,
                "trophies": 568
              }
            },
            {
              "tag": "#8P0PGYGY9",
              "name": "kevin",
              "brawler": {
                "id": 16000015,
                "name": "PIPER",
                "power": 11,
                "trophies": 991
              }
            }
          ],
          [
            {
              "tag": "#2Q920VYR02",
              "name": "\ud83d\udda4SirHimYT \ud83d\udda4",
              "brawler": {
                "id": 16000079,
                "name": "ANGELO",
                "power": 11,
                "trophies": 970
              }
            },
            {
              "tag": "#Y82QV2R9V",
              "name": "lukalu25",
              "brawler": {
                "id": 16000013,
                "name": "POCO",
                "power": 11,
                "trophies": 967
              }
            },
            {
              "tag": "#2LV0PLP8G",
              "name": "connorli",
              "brawler": {
                "id": 16000001,
                "name": "COLT",
                "power": 11,
                "trophies": 965
              }
            },
            {
              "tag": "#P88L8PPPL",
              "name": "YT]@$SWEAT@$",
              "brawler": {
                "id": 16000004,
                "name": "RICO",
                "power": 11,
                "trophies": 969
              }
            },
            {
              "tag": "#L2QQRPJJY",
              "name": "Dr golpes",
              "brawler": {
                "id": 16000023,
                "name": "LEON",
                "power": 11,
                "trophies": 965
              }
            }
          ]
        ]
      }
    },
    {
      "battleTime": "20250504T041512.000Z",
      "event": {
        "id": 15000700,
        "mode": "knockout5V5",
        "map": "Sizzling Chambers"
      },
      "battle": {
        "mode": "knockout",
        "type": "ranked",
        "result": "defeat",
        "duration": 204,
        "trophyChange": -7,
        "starPlayer": {
          "tag": "#2QRQY0PRU0",
          "name": "kevin is trash",
          "brawler": {
            "id": 16000015,
            "name": "PIPER",
            "power": 11,
            "trophies": 965
          }
        },
        "teams": [
          [
            {
              "tag": "#2GL22UCRLC",
              "name": "DuckForBeginner",
              "brawler": {
                "id": 16000069,
                "name": "HANK",
                "power": 11,
                "trophies": 970
              }
            },
            {
              "tag": "#2QVV9URQ29",
              "name": "papitas21",
              "brawler": {
                "id": 16000043,
                "name": "EDGAR",
                "power": 11,
                "trophies": 965
              }
            },
            {
              "tag": "#P2PVQ982V",
              "name": "Dylandxd",
              "brawler": {
                "id": 16000023,
                "name": "LEON",
                "power": 11,
                "trophies": 965
              }
            },
            {
              "tag": "#8P8U9LYUG",
              "name": "\ud835\udcd0\ud835\udcec\ud835\udcee",
              "brawler": {
                "id": 16000056,
                "name": "EVE",
                "power": 11,
                "trophies": 638
              }
            },
            {
              "tag": "#2QRQY0PRU0",
              "name": "kevin is trash",
              "brawler": {
                "id": 16000015,
                "name": "PIPER",
                "power": 11,
                "trophies": 965
              }
            }
          ],
          [
            {
              "tag": "#2LV0PLP8G",
              "name": "connorli",
              "brawler": {
                "id": 16000001,
                "name": "COLT",
                "power": 11,
                "trophies": 972
              }
            },
            {
              "tag": "#2R0CV22CUY",
              "name": "sraluluu",
              "brawler": {
                "id": 16000031,
                "name": "MR. P",
                "power": 8,
                "trophies": 255
              }
            },
            {
              "tag": "#2LGVU2YL0P",
              "name": "kim._.",
              "brawler": {
                "id": 16000043,
                "name": "EDGAR",
                "power": 11,
                "trophies": 995
              }
            },
            {
              "tag": "#8CJP0RQVY",
              "name": "Brawler",
              "brawler": {
                "id": 16000015,
                "name": "PIPER",
                "power": 11,
                "trophies": 950
              }
            },
            {
              "tag": "#2QY9UJVLV0",
              "name": "elenano",
              "brawler": {
                "id": 16000014,
                "name": "BO",
                "power": 11,
                "trophies": 1002
              }
            }
          ]
        ]
      }
    },
    {
      "battleTime": "20250504T040740.000Z",
      "event": {
        "id": 15000700,
        "mode": "knockout5V5",
        "map": "Sizzling Chambers"
      },
      "battle": {
        "mode": "knockout",
        "type": "ranked",
        "result": "victory",
        "duration": 242,
        "trophyChange": 8,
        "starPlayer": {
          "tag": "#2LR0UJ8R8P",
          "name": "hoy",
          "brawler": {
            "id": 16000001,
            "name": "COLT",
            "power": 11,
            "trophies": 950
          }
        },
        "teams": [
          [
            {
              "tag": "#P0Q2GPJLQ",
              "name": "Itachi Uchiha",
              "brawler": {
                "id": 16000012,
                "name": "CROW",
                "power": 11,
                "trophies": 924
              }
            },
            {
              "tag": "#Q00C8GQ9P",
              "name": "awakate \ud83c\uddf2\ud83c\uddfd",
              "brawler": {
                "id": 16000013,
                "name": "POCO",
                "power": 11,
                "trophies": 951
              }
            },
            {
              "tag": "#L0VP9QCV0",
              "name": "fresita\u2763\ufe0f",
              "brawler": {
                "id": 16000015,
                "name": "PIPER",
                "power": 11,
                "trophies": 583
              }
            },
            {
              "tag": "#2LR0UJ8R8P",
              "name": "hoy",
              "brawler": {
                "id": 16000001,
                "name": "COLT",
                "power": 11,
                "trophies": 950
              }
            },
            {
              "tag": "#P2UP90UCJ",
              "name": "OTP21",
              "brawler": {
                "id": 16000014,
                "name": "BO",
                "power": 11,
                "trophies": 974
              }
            }
          ],
          [
            {
              "tag": "#28Y2Y9UR9C",
              "name": "TOMOEMAMI",
              "brawler": {
                "id": 16000065,
                "name": "MANDY",
                "power": 11,
                "trophies": 964
              }
            },
            {
              "tag": "#9CVLR9GPY",
              "name": "JIAFEI",
              "brawler": {
                "id": 16000069,
                "name": "HANK",
                "power": 11,
                "trophies": 562
              }
            },
            {
              "tag": "#2J90V2YY",
              "name": "Kevin\u1d41\u1d5a\u1d41",
              "brawler": {
                "id": 16000015,
                "name": "PIPER",
                "power": 11,
                "trophies": 968
              }
            },
            {
              "tag": "#2LV0PLP8G",
              "name": "connorli",
              "brawler": {
                "id": 16000001,
                "name": "COLT",
                "power": 11,
                "trophies": 964
              }
            },
            {
              "tag": "#QRP0GC2LQ",
              "name": "wilfredo",
              "brawler": {
                "id": 16000022,
                "name": "TICK",
                "power": 11,
                "trophies": 934
              }
            }
          ]
        ]
      }
    },
    {
      "battleTime": "20250504T040309.000Z",
      "event": {
        "id": 15000700,
        "mode": "knockout5V5",
        "map": "Sizzling Chambers"
      },
      "battle": {
        "mode": "knockout",
        "type": "ranked",
        "result": "defeat",
        "duration": 283,
        "trophyChange": -7,
        "starPlayer": {
          "tag": "#8RLCJLGQ9",
          "name": ":)",
          "brawler": {
            "id": 16000079,
            "name": "ANGELO",
            "power": 11,
            "trophies": 992
          }
        },
        "teams": [
          [
            {
              "tag": "#2J2G2CL9U",
              "name": "\u26a1MIGUEL\u26a1",
              "brawler": {
                "id": 16000003,
                "name": "BROCK",
                "power": 11,
                "trophies": 974
              }
            },
            {
              "tag": "#2LV0PLP8G",
              "name": "connorli",
              "brawler": {
                "id": 16000001,
                "name": "COLT",
                "power": 11,
                "trophies": 971
              }
            },
            {
              "tag": "#2GQVCQR9GY",
              "name": "?!",
              "brawler": {
                "id": 16000043,
                "name": "EDGAR",
                "power": 11,
                "trophies": 970
              }
            },
            {
              "tag": "#92RCCPQVC",
              "name": "jonavilla23",
              "brawler": {
                "id": 16000085,
                "name": "KENJI",
                "power": 11,
                "trophies": 928
              }
            },
            {
              "tag": "#89GC0RQ2Y",
              "name": "eddiewei",
              "brawler": {
                "id": 16000022,
                "name": "TICK",
                "power": 10,
                "trophies": 987
              }
            }
          ],
          [
            {
              "tag": "#2UVCUCGGY",
              "name": "lickmypuebes",
              "brawler": {
                "id": 16000001,
                "name": "COLT",
                "power": 11,
                "trophies": 527
              }
            },
            {
              "tag": "#YYY0YU9R",
              "name": "Big daddy",
              "brawler": {
                "id": 16000004,
                "name": "RICO",
                "power": 11,
                "trophies": 626
              }
            },
            {
              "tag": "#8RLCJLGQ9",
              "name": ":)",
              "brawler": {
                "id": 16000079,
                "name": "ANGELO",
                "power": 11,
                "trophies": 992
              }
            },
            {
              "tag": "#QRL8YYQ2L",
              "name": "DemonTimeSlopp",
              "brawler": {
                "id": 16000038,
                "name": "SURGE",
                "power": 11,
                "trophies": 932
              }
            },
            {
              "tag": "#P88LGPCGY",
              "name": "dylan",
              "brawler": {
                "id": 16000043,
                "name": "EDGAR",
                "power": 11,
                "trophies": 996
              }
            }
          ]
        ]
      }
    },
    {
      "battleTime": "20250504T035743.000Z",
      "event": {
        "id": 15000700,
        "mode": "knockout5V5",
        "map": "Sizzling Chambers"
      },
      "battle": {
        "mode": "knockout",
        "type": "ranked",
        "result": "defeat",
        "duration": 268,
        "trophyChange": -7,
        "starPlayer": {
          "tag": "#2URLVC222",
          "name": "Karl Marx",
          "brawler": {
            "id": 16000015,
            "name": "PIPER",
            "power": 11,
            "trophies": 967
          }
        },
        "teams": [
          [
            {
              "tag": "#GJPPPC0QP",
              "name": ":)",
              "brawler": {
                "id": 16000038,
                "name": "SURGE",
                "power": 11,
                "trophies": 993
              }
            },
            {
              "tag": "#YCLYQGC2R",
              "name": "dIeGo12",
              "brawler": {
                "id": 16000042,
                "name": "BYRON",
                "power": 11,
                "trophies": 927
              }
            },
            {
              "tag": "#G2U8JY9L0",
              "name": "abuelo the one",
              "brawler": {
                "id": 16000003,
                "name": "BROCK",
                "power": 11,
                "trophies": 1000
              }
            },
            {
              "tag": "#98880VQ2Y",
              "name": "Andrews25xdd",
              "brawler": {
                "id": 16000009,
                "name": "DYNAMIKE",
                "power": 11,
                "trophies": 993
              }
            },
            {
              "tag": "#2LV0PLP8G",
              "name": "connorli",
              "brawler": {
                "id": 16000001,
                "name": "COLT",
                "power": 11,
                "trophies": 978
              }
            }
          ],
          [
            {
              "tag": "#2L0C82J928",
              "name": "xim sau",
              "brawler": {
                "id": 16000006,
                "name": "BARLEY",
                "power": 11,
                "trophies": 974
              }
            },
            {
              "tag": "#2YVJ02PG0Q",
              "name": "Dantilos:V",
              "brawler": {
                "id": 16000042,
                "name": "BYRON",
                "power": 10,
                "trophies": 342
              }
            },
            {
              "tag": "#GYQGVUGPR",
              "name": "bimboodoll",
              "brawler": {
                "id": 16000022,
                "name": "TICK",
                "power": 9,
                "trophies": 948
              }
            },
            {
              "tag": "#2Q0JP09JYY",
              "name": "lamaslesbi",
              "brawler": {
                "id": 16000010,
                "name": "EL PRIMO",
                "power": 11,
                "trophies": 973
              }
            },
            {
              "tag": "#2URLVC222",
              "name": "Karl Marx",
              "brawler": {
                "id": 16000015,
                "name": "PIPER",
                "power": 11,
                "trophies": 967
              }
            }
          ]
        ]
      }
    },
    {
      "battleTime": "20250504T021022.000Z",
      "event": {
        "id": 15000700,
        "mode": "knockout5V5",
        "map": "Sizzling Chambers"
      },
      "battle": {
        "mode": "knockout",
        "type": "ranked",
        "result": "defeat",
        "duration": 191,
        "trophyChange": -7,
        "starPlayer": {
          "tag": "#G9C000CQ2",
          "name": "\u2667\u00c2c\u0113\u2664",
          "brawler": {
            "id": 16000015,
            "name": "PIPER",
            "power": 11,
            "trophies": 986
          }
        },
        "teams": [
          [
            {
              "tag": "#G9C000CQ2",
              "name": "\u2667\u00c2c\u0113\u2664",
              "brawler": {
                "id": 16000015,
                "name": "PIPER",
                "power": 11,
                "trophies": 986
              }
            },
            {
              "tag": "#2QQCLLJ008",
              "name": "JB_\ud835\udcae\u210b\ud835\udcaa\ud835\udca2\ud835\udcb0\ud835\udca9",
              "brawler": {
                "id": 16000038,
                "name": "SURGE",
                "power": 10,
                "trophies": 744
              }
            },
            {
              "tag": "#2RRUJGUGC9",
              "name": "jairo",
              "brawler": {
                "id": 16000043,
                "name": "EDGAR",
                "power": 11,
                "trophies": 951
              }
            },
            {
              "tag": "#PJCQJGJ8Y",
              "name": "Best Panda",
              "brawler": {
                "id": 16000001,
                "name": "COLT",
                "power": 11,
                "trophies": 965
              }
            },
            {
              "tag": "#28GJ8QG2Y",
              "name": "8cholady",
              "brawler": {
                "id": 16000022,
                "name": "TICK",
                "power": 11,
                "trophies": 957
              }
            }
          ],
          [
            {
              "tag": "#28QGRGJYV",
              "name": "smd",
              "brawler": {
                "id": 16000048,
                "name": "GROM",
                "power": 11,
                "trophies": 981
              }
            },
            {
              "tag": "#GJU2RV2RV",
              "name": "SWE|fred\ud83d\ude0d\ud83e\udd70\ud83d\ude18",
              "brawler": {
                "id": 16000015,
                "name": "PIPER",
                "power": 10,
                "trophies": 953
              }
            },
            {
              "tag": "#GGRYVVP8V",
              "name": "bread",
              "brawler": {
                "id": 16000022,
                "name": "TICK",
                "power": 11,
                "trophies": 798
              }
            },
            {
              "tag": "#2LV0PLP8G",
              "name": "connorli",
              "brawler": {
                "id": 16000001,
                "name": "COLT",
                "power": 11,
                "trophies": 985
              }
            },
            {
              "tag": "#28QU2LV29R",
              "name": "JASON",
              "brawler": {
                "id": 16000043,
                "name": "EDGAR",
                "power": 11,
                "trophies": 966
              }
            }
          ]
        ]
      }
    },
    {
      "battleTime": "20250504T011202.000Z",
      "event": {
        "id": 15000700,
        "mode": "knockout5V5",
        "map": "Sizzling Chambers"
      },
      "battle": {
        "mode": "knockout",
        "type": "ranked",
        "result": "defeat",
        "duration": 175,
        "trophyChange": -7,
        "starPlayer": {
          "tag": "#QRL2CV8R",
          "name": "Dexter",
          "brawler": {
            "id": 16000065,
            "name": "MANDY",
            "power": 11,
            "trophies": 978
          }
        },
        "teams": [
          [
            {
              "tag": "#Q0C0QG8J2",
              "name": "AUX_BlueBerry",
              "brawler": {
                "id": 16000087,
                "name": "JUJU",
                "power": 11,
                "trophies": 997
              }
            },
            {
              "tag": "#LV9QQLR08",
              "name": "nguyentran",
              "brawler": {
                "id": 16000010,
                "name": "EL PRIMO",
                "power": 11,
                "trophies": 505
              }
            },
            {
              "tag": "#2Q8LYCC9",
              "name": "leaf",
              "brawler": {
                "id": 16000013,
                "name": "POCO",
                "power": 11,
                "trophies": 886
              }
            },
            {
              "tag": "#2898CGQUU",
              "name": "thedoge",
              "brawler": {
                "id": 16000023,
                "name": "LEON",
                "power": 11,
                "trophies": 567
              }
            },
            {
              "tag": "#2LV0PLP8G",
              "name": "connorli",
              "brawler": {
                "id": 16000001,
                "name": "COLT",
                "power": 11,
                "trophies": 992
              }
            }
          ],
          [
            {
              "tag": "#2QRLGUR8YQ",
              "name": "THE PRIMEAPE",
              "brawler": {
                "id": 16000013,
                "name": "POCO",
                "power": 11,
                "trophies": 869
              }
            },
            {
              "tag": "#QRL2CV8R",
              "name": "Dexter",
              "brawler": {
                "id": 16000065,
                "name": "MANDY",
                "power": 11,
                "trophies": 978
              }
            },
            {
              "tag": "#GYUQYYC2R",
              "name": "T0RVAX",
              "brawler": {
                "id": 16000025,
                "name": "CARL",
                "power": 11,
                "trophies": 892
              }
            },
            {
              "tag": "#2YYJ8CG8LQ",
              "name": "kingTona",
              "brawler": {
                "id": 16000040,
                "name": "AMBER",
                "power": 11,
                "trophies": 992
              }
            },
            {
              "tag": "#LVUU9V9Y0",
              "name": "N\u00ec\u00fe\u0125\u0259\u0155\u2661",
              "brawler": {
                "id": 16000003,
                "name": "BROCK",
                "power": 11,
                "trophies": 985
              }
            }
          ]
        ]
      }
    }
  ],
  "paging": {
    "cursors": {}
  }
}