{
  "items": [
    {
      "battleTime": "20250210T050208.000Z",
      "event": {
        "id": 15000853,
        "mode": "unknown",
        "map": "Below Zero"
      },
      "battle": {
        "mode": "brawlBall",
        "type": "ranked",
        "result": "defeat",
        "duration": 150,
        "trophyChange": -2,
        "starPlayer": {
          "tag": "#P2LCLUYU",
          "name": "Tu bby es mia;)",
          "brawler": {
            "id": 16000022,
            "name": "TICK",
            "power": 9,
            "trophies": 133
          }
        },
        "teams": [
          [
            {
              "tag": "#82Y9Q8GVL",
              "name": "YahirTrebol",
              "brawler": {
                "id": 16000072,
                "name": "PEARL",
                "power": 8,
                "trophies": 202
              }
            },
            {
              "tag": "#P2LCLUYU",
              "name": "Tu bby es mia;)",
              "brawler": {
                "id": 16000022,
                "name": "TICK",
                "power": 9,
                "trophies": 133
              }
            },
            {
              "tag": "#Q0L9GRLLP",
              "name": "jojojob",
              "brawler": {
                "id": 16000056,
                "name": "EVE",
                "power": 7,
                "trophies": 201
              }
            }
          ],
          [
            {
              "tag": "#LV9QQLR08",
              "name": "nguyentran",
              "brawler": {
                "id": 16000085,
                "name": "KENJI",
                "power": 9,
                "trophies": 220
              }
            },
            {
              "tag": "#LQQYGCV29",
              "name": "colin",
              "brawler": {
                "id": 16000089,
                "name": "MEEPLE",
                "power": 9,
                "trophies": 89
              }
            },
            {
              "tag": "#2G0JQ2Q0YQ",
              "name": "GlizzyPistol",
              "brawler": {
                "id": 16000007,
                "name": "JESSIE",
                "power": 9,
                "trophies": 143
              }
            }
          ]
        ]
      }
    },
    {
      "battleTime": "20250210T045809.000Z",
      "event": {
        "id": 15000019,
        "mode": "heist",
        "map": "Safe Zone"
      },
      "battle": {
        "mode": "heist",
        "type": "soloRanked",
        "result": "victory",
        "duration": 146,
        "starPlayer": {
          "tag": "#GQ0929GJ2",
          "name": "Jipson Nub",
          "brawler": {
            "id": 16000054,
            "name": "FANG",
            "power": 11,
            "trophies": 5
          }
        },
        "teams": [
          [
            {
              "tag": "#LV9QQLR08",
              "name": "nguyentran",
              "brawler": {
                "id": 16000003,
                "name": "BROCK",
                "power": 9,
                "trophies": 5
              }
            },
            {
              "tag": "#GQ0929GJ2",
              "name": "Jipson Nub",
              "brawler": {
                "id": 16000054,
                "name": "FANG",
                "power": 11,
                "trophies": 5
              }
            },
            {
              "tag": "#2G088JU0RV",
              "name": "Adonai\u2022\ud83c\udf00\ud83c\udfa7",
              "brawler": {
                "id": 16000065,
                "name": "MANDY",
                "power": 11,
                "trophies": 5
              }
            }
          ],
          [
            {
              "tag": "#22RUJRJY",
              "name": "lux",
              "brawler": {
                "id": 16000001,
                "name": "COLT",
                "power": 11,
                "trophies": 5
              }
            },
            {
              "tag": "#9YJR88829",
              "name": "Juan|Caca",
              "brawler": {
                "id": 16000037,
                "name": "SPROUT",
                "power": 11,
                "trophies": 5
              }
            },
            {
              "tag": "#2YQL820RL2",
              "name": "CACA MAN 1234",
              "brawler": {
                "id": 16000012,
                "name": "CROW",
                "power": 11,
                "trophies": 5
              }
            }
          ]
        ]
      }
    },
    {
      "battleTime": "20250210T045203.000Z",
      "event": {
        "id": 15000367,
        "mode": "knockout",
        "map": "Goldarm Gulch"
      },
      "battle": {
        "mode": "knockout",
        "type": "soloRanked",
        "result": "victory",
        "duration": 56,
        "starPlayer": {
          "tag": "#LGR0YYV2",
          "name": "Arminh",
          "brawler": {
            "id": 16000043,
            "name": "EDGAR",
            "power": 11,
            "trophies": 6
          }
        },
        "teams": [
          [
            {
              "tag": "#LGR0YYV2",
              "name": "Arminh",
              "brawler": {
                "id": 16000043,
                "name": "EDGAR",
                "power": 11,
                "trophies": 6
              }
            },
            {
              "tag": "#LV9QQLR08",
              "name": "nguyentran",
              "brawler": {
                "id": 16000011,
                "name": "MORTIS",
                "power": 9,
                "trophies": 5
              }
            },
            {
              "tag": "#LQQYGCV29",
              "name": "colin",
              "brawler": {
                "id": 16000014,
                "name": "BO",
                "power": 10,
                "trophies": 5
              }
            }
          ],
          [
            {
              "tag": "#JCQUULU09",
              "name": "maraa",
              "brawler": {
                "id": 16000051,
                "name": "ASH",
                "power": 9,
                "trophies": 608
              }
            },
            {
              "tag": "#JCLQRUURY",
              "name": "Hyra",
              "brawler": {
                "id": 16000001,
                "name": "COLT",
                "power": 11,
                "trophies": 603
              }
            },
            {
              "tag": "#JCQRPRLJQ",
              "name": "sasa thg",
              "brawler": {
                "id": 16000024,
                "name": "ROSA",
                "power": 11,
                "trophies": 593
              }
            }
          ]
        ]
      }
    },
    {
      "battleTime": "20250210T044958.000Z",
      "event": {
        "id": 15000004,
        "mode": "bounty",
        "map": "Snake Prairie"
      },
      "battle": {
        "mode": "bounty",
        "type": "soloRanked",
        "result": "defeat",
        "duration": 74,
        "starPlayer": {
          "tag": "#Y0J2VJURV",
          "name": "Juls",
          "brawler": {
            "id": 16000049,
            "name": "BUZZ",
            "power": 10,
            "trophies": 5
          }
        },
        "teams": [
          [
            {
              "tag": "#2QP008P9V0",
              "name": "\u5f61\ud835\udd5c\ud835\udd63\ud835\udd5a\ud835\udd64\u2740",
              "brawler": {
                "id": 16000000,
                "name": "SHELLY",
                "power": 9,
                "trophies": 5
              }
            },
            {
              "tag": "#LV9QQLR08",
              "name": "nguyentran",
              "brawler": {
                "id": 16000034,
                "name": "JACKY",
                "power": 11,
                "trophies": 5
              }
            },
            {
              "tag": "#LQQYGCV29",
              "name": "colin",
              "brawler": {
                "id": 16000024,
                "name": "ROSA",
                "power": 11,
                "trophies": 5
              }
            }
          ],
          [
            {
              "tag": "#Q92QJCRVC",
              "name": "Brawl",
              "brawler": {
                "id": 16000043,
                "name": "EDGAR",
                "power": 11,
                "trophies": 5
              }
            },
            {
              "tag": "#Y0J2VJURV",
              "name": "Juls",
              "brawler": {
                "id": 16000049,
                "name": "BUZZ",
                "power": 10,
                "trophies": 5
              }
            },
            {
              "tag": "#20CQYJRVG",
              "name": "\u0280\u025b\u01df\u029f\u04c4\u0268\u057c\u0262",
              "brawler": {
                "id": 16000035,
                "name": "GALE",
                "power": 11,
                "trophies": 5
              }
            }
          ]
        ]
      }
    },
    {
      "battleTime": "20250210T044740.000Z",
      "event": {
        "id": 15000054,
        "mode": "bounty",
        "map": "Canal Grande"
      },
      "battle": {
        "mode": "bounty",
        "type": "soloRanked",
        "result": "defeat",
        "duration": 68,
        "starPlayer": {
          "tag": "#PLQGRC0P",
          "name": "ytMingonator87",
          "brawler": {
            "id": 16000048,
            "name": "GROM",
            "power": 11,
            "trophies": 5
          }
        },
        "teams": [
          [
            {
              "tag": "#GQC9RQGQJ",
              "name": "haus maus",
              "brawler": {
                "id": 16000034,
                "name": "JACKY",
                "power": 11,
                "trophies": 5
              }
            },
            {
              "tag": "#2LJRJVJY9C",
              "name": "Ilove hockey",
              "brawler": {
                "id": 16000043,
                "name": "EDGAR",
                "power": 10,
                "trophies": 5
              }
            },
            {
              "tag": "#PLQGRC0P",
              "name": "ytMingonator87",
              "brawler": {
                "id": 16000048,
                "name": "GROM",
                "power": 11,
                "trophies": 5
              }
            }
          ],
          [
            {
              "tag": "#2QVYVYLPPU",
              "name": "Mile",
              "brawler": {
                "id": 16000020,
                "name": "FRANK",
                "power": 10,
                "trophies": 5
              }
            },
            {
              "tag": "#LV9QQLR08",
              "name": "nguyentran",
              "brawler": {
                "id": 16000009,
                "name": "DYNAMIKE",
                "power": 10,
                "trophies": 5
              }
            },
            {
              "tag": "#LQQYGCV29",
              "name": "colin",
              "brawler": {
                "id": 16000071,
                "name": "DOUG",
                "power": 10,
                "trophies": 5
              }
            }
          ]
        ]
      }
    },
    {
      "battleTime": "20250210T044549.000Z",
      "event": {
        "id": 15000368,
        "mode": "knockout",
        "map": "Belle's Rock"
      },
      "battle": {
        "mode": "knockout",
        "type": "soloRanked",
        "result": "victory",
        "duration": 90,
        "starPlayer": {
          "tag": "#LV9QQLR08",
          "name": "nguyentran",
          "brawler": {
            "id": 16000009,
            "name": "DYNAMIKE",
            "power": 10,
            "trophies": 5
          }
        },
        "teams": [
          [
            {
              "tag": "#LY800YRRL",
              "name": "Ragnar",
              "brawler": {
                "id": 16000003,
                "name": "BROCK",
                "power": 11,
                "trophies": 4
              }
            },
            {
              "tag": "#GQ9C8PV99",
              "name": "LilxMenol",
              "brawler": {
                "id": 16000025,
                "name": "CARL",
                "power": 9,
                "trophies": 5
              }
            },
            {
              "tag": "#2QGL9RV000",
              "name": "el mejor",
              "brawler": {
                "id": 16000004,
                "name": "RICO",
                "power": 9,
                "trophies": 5
              }
            }
          ],
          [
            {
              "tag": "#LV9QQLR08",
              "name": "nguyentran",
              "brawler": {
                "id": 16000009,
                "name": "DYNAMIKE",
                "power": 10,
                "trophies": 5
              }
            },
            {
              "tag": "#LQQYGCV29",
              "name": "colin",
              "brawler": {
                "id": 16000056,
                "name": "EVE",
                "power": 9,
                "trophies": 5
              }
            },
            {
              "tag": "#GRPYP8RC",
              "name": "\u5f61[Agness]\u5f61",
              "brawler": {
                "id": 16000048,
                "name": "GROM",
                "power": 11,
                "trophies": 5
              }
            }
          ]
        ]
      }
    },
    {
      "battleTime": "20250210T044146.000Z",
      "event": {
        "id": 15000011,
        "mode": "gemGrab",
        "map": "Undermine"
      },
      "battle": {
        "mode": "gemGrab",
        "type": "soloRanked",
        "result": "victory",
        "duration": 79,
        "starPlayer": {
          "tag": "#LV9QQLR08",
          "name": "nguyentran",
          "brawler": {
            "id": 16000005,
            "name": "SPIKE",
            "power": 11,
            "trophies": 5
          }
        },
        "teams": [
          [
            {
              "tag": "#LV9QQLR08",
              "name": "nguyentran",
              "brawler": {
                "id": 16000005,
                "name": "SPIKE",
                "power": 11,
                "trophies": 5
              }
            },
            {
              "tag": "#LQQYGCV29",
              "name": "colin",
              "brawler": {
                "id": 16000003,
                "name": "BROCK",
                "power": 9,
                "trophies": 4
              }
            },
            {
              "tag": "#2YCPRPLCU2",
              "name": "CeSaR7EqUiHuA",
              "brawler": {
                "id": 16000014,
                "name": "BO",
                "power": 11,
                "trophies": 6
              }
            }
          ],
          [
            {
              "tag": "#8C9UJGJPL",
              "name": "McQueen",
              "brawler": {
                "id": 16000050,
                "name": "GRIFF",
                "power": 10,
                "trophies": 508
              }
            },
            {
              "tag": "#8C8CLCRP8",
              "name": "\u30b7\u30a8\u30b9\u30bf",
              "brawler": {
                "id": 16000008,
                "name": "NITA",
                "power": 10,
                "trophies": 503
              }
            },
            {
              "tag": "#8CPL2Q8CU",
              "name": "maxibien",
              "brawler": {
                "id": 16000032,
                "name": "MAX",
                "power": 11,
                "trophies": 495
              }
            }
          ]
        ]
      }
    },
    {
      "battleTime": "20250210T043929.000Z",
      "event": {
        "id": 15000007,
        "mode": "gemGrab",
        "map": "Hard Rock Mine"
      },
      "battle": {
        "mode": "gemGrab",
        "type": "soloRanked",
        "result": "defeat",
        "duration": 95,
        "starPlayer": {
          "tag": "#UJQ8QL20R",
          "name": "acu\u00f1a2.0\ud83d\udc7b",
          "brawler": {
            "id": 16000063,
            "name": "CHESTER",
            "power": 10,
            "trophies": 5
          }
        },
        "teams": [
          [
            {
              "tag": "#LV9QQLR08",
              "name": "nguyentran",
              "brawler": {
                "id": 16000001,
                "name": "COLT",
                "power": 10,
                "trophies": 5
              }
            },
            {
              "tag": "#LQQYGCV29",
              "name": "colin",
              "brawler": {
                "id": 16000005,
                "name": "SPIKE",
                "power": 11,
                "trophies": 5
              }
            },
            {
              "tag": "#2LLJ2CULVU",
              "name": "ANTHOO",
              "brawler": {
                "id": 16000023,
                "name": "LEON",
                "power": 11,
                "trophies": 5
              }
            }
          ],
          [
            {
              "tag": "#UJQ8QL20R",
              "name": "acu\u00f1a2.0\ud83d\udc7b",
              "brawler": {
                "id": 16000063,
                "name": "CHESTER",
                "power": 10,
                "trophies": 5
              }
            },
            {
              "tag": "#ULPLJY0J9",
              "name": "sasuke",
              "brawler": {
                "id": 16000014,
                "name": "BO",
                "power": 10,
                "trophies": 4
              }
            },
            {
              "tag": "#LGCYY28QL",
              "name": "Naruto",
              "brawler": {
                "id": 16000049,
                "name": "BUZZ",
                "power": 11,
                "trophies": 5
              }
            }
          ]
        ]
      }
    },
    {
      "battleTime": "20250210T043657.000Z",
      "event": {
        "id": 15000132,
        "mode": "brawlBall",
        "map": "Center Stage"
      },
      "battle": {
        "mode": "brawlBall",
        "type": "soloRanked",
        "result": "defeat",
        "duration": 88,
        "starPlayer": {
          "tag": "#PG9VLU8Y",
          "name": "pro",
          "brawler": {
            "id": 16000009,
            "name": "DYNAMIKE",
            "power": 11,
            "trophies": 5
          }
        },
        "teams": [
          [
            {
              "tag": "#2L8PPUYV9C",
              "name": "Dasaani_Hater",
              "brawler": {
                "id": 16000004,
                "name": "RICO",
                "power": 11,
                "trophies": 5
              }
            },
            {
              "tag": "#8QCVGRQ29",
              "name": "(DIAMOND) S-2",
              "brawler": {
                "id": 16000026,
                "name": "BIBI",
                "power": 11,
                "trophies": 3
              }
            },
            {
              "tag": "#PG9VLU8Y",
              "name": "pro",
              "brawler": {
                "id": 16000009,
                "name": "DYNAMIKE",
                "power": 11,
                "trophies": 5
              }
            }
          ],
          [
            {
              "tag": "#LV9QQLR08",
              "name": "nguyentran",
              "brawler": {
                "id": 16000034,
                "name": "JACKY",
                "power": 11,
                "trophies": 5
              }
            },
            {
              "tag": "#LQQYGCV29",
              "name": "colin",
              "brawler": {
                "id": 16000005,
                "name": "SPIKE",
                "power": 11,
                "trophies": 5
              }
            },
            {
              "tag": "#2GUG9RP29U",
              "name": "star_Miri",
              "brawler": {
                "id": 16000035,
                "name": "GALE",
                "power": 9,
                "trophies": 5
              }
            }
          ]
        ]
      }
    },
    {
      "battleTime": "20250210T043432.000Z",
      "event": {
        "id": 15000005,
        "mode": "bounty",
        "map": "Shooting Star"
      },
      "battle": {
        "mode": "bounty",
        "type": "soloRanked",
        "result": "victory",
        "duration": 69,
        "starPlayer": {
          "tag": "#YJGC9VJPQ",
          "name": "XirCo",
          "brawler": {
            "id": 16000056,
            "name": "EVE",
            "power": 11,
            "trophies": 5
          }
        },
        "teams": [
          [
            {
              "tag": "#YLL9URL2U",
              "name": "Pro Gamer",
              "brawler": {
                "id": 16000001,
                "name": "COLT",
                "power": 11,
                "trophies": 4
              }
            },
            {
              "tag": "#QLLYQVVQV",
              "name": "..\u211f\ud835\udcea\ud835\udcc0\ud835\udcea\ud835\udd5f\ud835\udc52\ud83e\udd40",
              "brawler": {
                "id": 16000015,
                "name": "PIPER",
                "power": 11,
                "trophies": 5
              }
            },
            {
              "tag": "#RY280JYRL",
              "name": "Focus",
              "brawler": {
                "id": 16000045,
                "name": "STU",
                "power": 11,
                "trophies": 5
              }
            }
          ],
          [
            {
              "tag": "#LQQYGCV29",
              "name": "colin",
              "brawler": {
                "id": 16000003,
                "name": "BROCK",
                "power": 9,
                "trophies": 4
              }
            },
            {
              "tag": "#LV9QQLR08",
              "name": "nguyentran",
              "brawler": {
                "id": 16000009,
                "name": "DYNAMIKE",
                "power": 10,
                "trophies": 5
              }
            },
            {
              "tag": "#YJGC9VJPQ",
              "name": "XirCo",
              "brawler": {
                "id": 16000056,
                "name": "EVE",
                "power": 11,
                "trophies": 5
              }
            }
          ]
        ]
      }
    },
    {
      "battleTime": "20250210T043054.000Z",
      "event": {
        "id": 15000053,
        "mode": "heist",
        "map": "Hot Potato"
      },
      "battle": {
        "mode": "heist",
        "type": "soloRanked",
        "result": "defeat",
        "duration": 66,
        "starPlayer": {
          "tag": "#CLJP9989G",
          "name": "truelolo",
          "brawler": {
            "id": 16000004,
            "name": "RICO",
            "power": 11,
            "trophies": 5
          }
        },
        "teams": [
          [
            {
              "tag": "#LV9QQLR08",
              "name": "nguyentran",
              "brawler": {
                "id": 16000001,
                "name": "COLT",
                "power": 10,
                "trophies": 5
              }
            },
            {
              "tag": "#LQQYGCV29",
              "name": "colin",
              "brawler": {
                "id": 16000005,
                "name": "SPIKE",
                "power": 11,
                "trophies": 5
              }
            },
            {
              "tag": "#2LURPQRPLQ",
              "name": "jinx\ud83d\ude08",
              "brawler": {
                "id": 16000048,
                "name": "GROM",
                "power": 9,
                "trophies": 5
              }
            }
          ],
          [
            {
              "tag": "#CLJP9989G",
              "name": "truelolo",
              "brawler": {
                "id": 16000004,
                "name": "RICO",
                "power": 11,
                "trophies": 5
              }
            },
            {
              "tag": "#Q8UV2CJJ",
              "name": "omeezy\ud83d\ude2b",
              "brawler": {
                "id": 16000007,
                "name": "JESSIE",
                "power": 11,
                "trophies": 2
              }
            },
            {
              "tag": "#QY90Q9JJQ",
              "name": "\ud83d\udca6FROSTIE\ud83d\udcab",
              "brawler": {
                "id": 16000019,
                "name": "PENNY",
                "power": 11,
                "trophies": 5
              }
            }
          ]
        ]
      }
    },
    {
      "battleTime": "20250210T042853.000Z",
      "event": {
        "id": 15000025,
        "mode": "brawlBall",
        "map": "Triple Dribble"
      },
      "battle": {
        "mode": "brawlBall",
        "type": "soloRanked",
        "result": "victory",
        "duration": 150,
        "starPlayer": {
          "tag": "#LV9QQLR08",
          "name": "nguyentran",
          "brawler": {
            "id": 16000034,
            "name": "JACKY",
            "power": 11,
            "trophies": 4
          }
        },
        "teams": [
          [
            {
              "tag": "#28CV9V0LR",
              "name": "Parkour1776",
              "brawler": {
                "id": 16000026,
                "name": "BIBI",
                "power": 11,
                "trophies": 4
              }
            },
            {
              "tag": "#2GUUUG2PPQ",
              "name": "j.j17",
              "brawler": {
                "id": 16000050,
                "name": "GRIFF",
                "power": 9,
                "trophies": 4
              }
            },
            {
              "tag": "#2LCPC08RJU",
              "name": "sojan",
              "brawler": {
                "id": 16000043,
                "name": "EDGAR",
                "power": 11,
                "trophies": 4
              }
            }
          ],
          [
            {
              "tag": "#LV9QQLR08",
              "name": "nguyentran",
              "brawler": {
                "id": 16000034,
                "name": "JACKY",
                "power": 11,
                "trophies": 4
              }
            },
            {
              "tag": "#LQQYGCV29",
              "name": "colin",
              "brawler": {
                "id": 16000014,
                "name": "BO",
                "power": 10,
                "trophies": 4
              }
            },
            {
              "tag": "#URG2RYQR",
              "name": "Batsforever",
              "brawler": {
                "id": 16000035,
                "name": "GALE",
                "power": 11,
                "trophies": 4
              }
            }
          ]
        ]
      }
    },
    {
      "battleTime": "20250210T042539.000Z",
      "event": {
        "id": 15000005,
        "mode": "bounty",
        "map": "Shooting Star"
      },
      "battle": {
        "mode": "bounty",
        "type": "soloRanked",
        "result": "defeat",
        "duration": 89,
        "starPlayer": {
          "tag": "#2PCGGUP9UY",
          "name": "Jason",
          "brawler": {
            "id": 16000020,
            "name": "FRANK",
            "power": 11,
            "trophies": 4
          }
        },
        "teams": [
          [
            {
              "tag": "#LV9QQLR08",
              "name": "nguyentran",
              "brawler": {
                "id": 16000009,
                "name": "DYNAMIKE",
                "power": 10,
                "trophies": 4
              }
            },
            {
              "tag": "#LQQYGCV29",
              "name": "colin",
              "brawler": {
                "id": 16000005,
                "name": "SPIKE",
                "power": 11,
                "trophies": 4
              }
            },
            {
              "tag": "#Q2JGQGQGV",
              "name": "Money love\ud83e\udd11",
              "brawler": {
                "id": 16000006,
                "name": "BARLEY",
                "power": 9,
                "trophies": 4
              }
            }
          ],
          [
            {
              "tag": "#LY8UJ82UY",
              "name": "teddy",
              "brawler": {
                "id": 16000015,
                "name": "PIPER",
                "power": 11,
                "trophies": 4
              }
            },
            {
              "tag": "#80QP0RJCQ",
              "name": "TX|Choco\ud83c\udf6b",
              "brawler": {
                "id": 16000064,
                "name": "GRAY",
                "power": 11,
                "trophies": 4
              }
            },
            {
              "tag": "#2PCGGUP9UY",
              "name": "Jason",
              "brawler": {
                "id": 16000020,
                "name": "FRANK",
                "power": 11,
                "trophies": 4
              }
            }
          ]
        ]
      }
    },
    {
      "battleTime": "20250210T042306.000Z",
      "event": {
        "id": 15000306,
        "mode": "hotZone",
        "map": "Dueling Beetles"
      },
      "battle": {
        "mode": "hotZone",
        "type": "soloRanked",
        "result": "victory",
        "duration": 70,
        "starPlayer": {
          "tag": "#LV9QQLR08",
          "name": "nguyentran",
          "brawler": {
            "id": 16000009,
            "name": "DYNAMIKE",
            "power": 10,
            "trophies": 4
          }
        },
        "teams": [
          [
            {
              "tag": "#LV9QQLR08",
              "name": "nguyentran",
              "brawler": {
                "id": 16000009,
                "name": "DYNAMIKE",
                "power": 10,
                "trophies": 4
              }
            },
            {
              "tag": "#LQQYGCV29",
              "name": "colin",
              "brawler": {
                "id": 16000005,
                "name": "SPIKE",
                "power": 11,
                "trophies": 4
              }
            },
            {
              "tag": "#2GJJ2LGC8Y",
              "name": "Katsuxdd",
              "brawler": {
                "id": 16000018,
                "name": "DARRYL",
                "power": 9,
                "trophies": 4
              }
            }
          ],
          [
            {
              "tag": "#8CP0RQQJL",
              "name": "Nikola",
              "brawler": {
                "id": 16000012,
                "name": "CROW",
                "power": 10,
                "trophies": 703
              }
            },
            {
              "tag": "#8C8UQYRC0",
              "name": "[MMA] FENIXC",
              "brawler": {
                "id": 16000061,
                "name": "GUS",
                "power": 10,
                "trophies": 707
              }
            },
            {
              "tag": "#8C9VVL8VG",
              "name": "youness",
              "brawler": {
                "id": 16000010,
                "name": "EL PRIMO",
                "power": 11,
                "trophies": 691
              }
            }
          ]
        ]
      }
    },
    {
      "battleTime": "20250210T042114.000Z",
      "event": {
        "id": 15000050,
        "mode": "brawlBall",
        "map": "Sneaky Fields"
      },
      "battle": {
        "mode": "brawlBall",
        "type": "soloRanked",
        "result": "defeat",
        "duration": 135,
        "starPlayer": {
          "tag": "#LV9QQLR08",
          "name": "nguyentran",
          "brawler": {
            "id": 16000034,
            "name": "JACKY",
            "power": 11,
            "trophies": 4
          }
        },
        "teams": [
          [
            {
              "tag": "#PUU0QCL92",
              "name": "Lock In Boys",
              "brawler": {
                "id": 16000003,
                "name": "BROCK",
                "power": 11,
                "trophies": 4
              }
            },
            {
              "tag": "#YG9909G0",
              "name": "Devon",
              "brawler": {
                "id": 16000026,
                "name": "BIBI",
                "power": 11,
                "trophies": 4
              }
            },
            {
              "tag": "#GG2RLVVPL",
              "name": "radiopapuu",
              "brawler": {
                "id": 16000030,
                "name": "EMZ",
                "power": 11,
                "trophies": 4
              }
            }
          ],
          [
            {
              "tag": "#LV9QQLR08",
              "name": "nguyentran",
              "brawler": {
                "id": 16000034,
                "name": "JACKY",
                "power": 11,
                "trophies": 4
              }
            },
            {
              "tag": "#LQQYGCV29",
              "name": "colin",
              "brawler": {
                "id": 16000005,
                "name": "SPIKE",
                "power": 11,
                "trophies": 4
              }
            },
            {
              "tag": "#8C9J8822",
              "name": "Jaelpro222",
              "brawler": {
                "id": 16000038,
                "name": "SURGE",
                "power": 11,
                "trophies": 4
              }
            }
          ]
        ]
      }
    },
    {
      "battleTime": "20250210T041814.000Z",
      "event": {
        "id": 15000367,
        "mode": "knockout",
        "map": "Goldarm Gulch"
      },
      "battle": {
        "mode": "knockout",
        "type": "soloRanked",
        "result": "defeat",
        "duration": 138,
        "starPlayer": {
          "tag": "#9CGQ0C99R",
          "name": "awesome sauce",
          "brawler": {
            "id": 16000023,
            "name": "LEON",
            "power": 11,
            "trophies": 4
          }
        },
        "teams": [
          [
            {
              "tag": "#G8YU98URR",
              "name": "jace",
              "brawler": {
                "id": 16000018,
                "name": "DARRYL",
                "power": 10,
                "trophies": 4
              }
            },
            {
              "tag": "#LV9QQLR08",
              "name": "nguyentran",
              "brawler": {
                "id": 16000009,
                "name": "DYNAMIKE",
                "power": 10,
                "trophies": 4
              }
            },
            {
              "tag": "#LQQYGCV29",
              "name": "colin",
              "brawler": {
                "id": 16000014,
                "name": "BO",
                "power": 10,
                "trophies": 4
              }
            }
          ],
          [
            {
              "tag": "#2YLYJ099JY",
              "name": "Gatopezz_69",
              "brawler": {
                "id": 16000005,
                "name": "SPIKE",
                "power": 11,
                "trophies": 4
              }
            },
            {
              "tag": "#9CGQ0C99R",
              "name": "awesome sauce",
              "brawler": {
                "id": 16000023,
                "name": "LEON",
                "power": 11,
                "trophies": 4
              }
            },
            {
              "tag": "#9VU0C8RJ9",
              "name": "GH",
              "brawler": {
                "id": 16000035,
                "name": "GALE",
                "power": 11,
                "trophies": 4
              }
            }
          ]
        ]
      }
    },
    {
      "battleTime": "20250210T041501.000Z",
      "event": {
        "id": 15000636,
        "mode": "gemGrab",
        "map": "Last Stop"
      },
      "battle": {
        "mode": "gemGrab",
        "type": "soloRanked",
        "result": "victory",
        "duration": 110,
        "starPlayer": {
          "tag": "#LV9QQLR08",
          "name": "nguyentran",
          "brawler": {
            "id": 16000001,
            "name": "COLT",
            "power": 10,
            "trophies": 4
          }
        },
        "teams": [
          [
            {
              "tag": "#2GGL09YPVY",
              "name": "yoniimsano\u2664",
              "brawler": {
                "id": 16000018,
                "name": "DARRYL",
                "power": 9,
                "trophies": 4
              }
            },
            {
              "tag": "#V808Y9CLU",
              "name": "I like gay guys",
              "brawler": {
                "id": 16000001,
                "name": "COLT",
                "power": 11,
                "trophies": 4
              }
            },
            {
              "tag": "#G8YLJ89PR",
              "name": "TTVALEXBTW",
              "brawler": {
                "id": 16000013,
                "name": "POCO",
                "power": 11,
                "trophies": 4
              }
            }
          ],
          [
            {
              "tag": "#QYUYLLGLY",
              "name": "I'm Jhonatan",
              "brawler": {
                "id": 16000015,
                "name": "PIPER",
                "power": 11,
                "trophies": 4
              }
            },
            {
              "tag": "#LV9QQLR08",
              "name": "nguyentran",
              "brawler": {
                "id": 16000001,
                "name": "COLT",
                "power": 10,
                "trophies": 4
              }
            },
            {
              "tag": "#LQQYGCV29",
              "name": "colin",
              "brawler": {
                "id": 16000005,
                "name": "SPIKE",
                "power": 11,
                "trophies": 4
              }
            }
          ]
        ]
      }
    },
    {
      "battleTime": "20250210T041215.000Z",
      "event": {
        "id": 15000132,
        "mode": "brawlBall",
        "map": "Center Stage"
      },
      "battle": {
        "mode": "brawlBall",
        "type": "soloRanked",
        "result": "victory",
        "duration": 101,
        "starPlayer": {
          "tag": "#LV9QQLR08",
          "name": "nguyentran",
          "brawler": {
            "id": 16000034,
            "name": "JACKY",
            "power": 11,
            "trophies": 4
          }
        },
        "teams": [
          [
            {
              "tag": "#GYPQ0LG0C",
              "name": "Fankz9\ud83d\udc7d",
              "brawler": {
                "id": 16000004,
                "name": "RICO",
                "power": 11,
                "trophies": 4
              }
            },
            {
              "tag": "#LV9QQLR08",
              "name": "nguyentran",
              "brawler": {
                "id": 16000034,
                "name": "JACKY",
                "power": 11,
                "trophies": 4
              }
            },
            {
              "tag": "#LQQYGCV29",
              "name": "colin",
              "brawler": {
                "id": 16000005,
                "name": "SPIKE",
                "power": 11,
                "trophies": 4
              }
            }
          ],
          [
            {
              "tag": "#209Y20YJ8Q",
              "name": "\ud83e\udd77 Carlos A.F\u2694\ufe0f",
              "brawler": {
                "id": 16000010,
                "name": "EL PRIMO",
                "power": 11,
                "trophies": 4
              }
            },
            {
              "tag": "#2GR0QP8L8V",
              "name": "Fernando",
              "brawler": {
                "id": 16000009,
                "name": "DYNAMIKE",
                "power": 9,
                "trophies": 4
              }
            },
            {
              "tag": "#RYLCVVJC0",
              "name": "18Shadows",
              "brawler": {
                "id": 16000000,
                "name": "SHELLY",
                "power": 11,
                "trophies": 4
              }
            }
          ]
        ]
      }
    },
    {
      "battleTime": "20250210T040933.000Z",
      "event": {
        "id": 15000019,
        "mode": "heist",
        "map": "Safe Zone"
      },
      "battle": {
        "mode": "heist",
        "type": "soloRanked",
        "result": "victory",
        "duration": 150,
        "starPlayer": {
          "tag": "#LQQYGCV29",
          "name": "colin",
          "brawler": {
            "id": 16000050,
            "name": "GRIFF",
            "power": 10,
            "trophies": 3
          }
        },
        "teams": [
          [
            {
              "tag": "#PJ2PC2QRU",
              "name": "Zoob",
              "brawler": {
                "id": 16000050,
                "name": "GRIFF",
                "power": 10,
                "trophies": 4
              }
            },
            {
              "tag": "#2L9JRYP2Y8",
              "name": "ElIngVikingo",
              "brawler": {
                "id": 16000042,
                "name": "BYRON",
                "power": 9,
                "trophies": 4
              }
            },
            {
              "tag": "#RLYVGYRG9",
              "name": "countercat",
              "brawler": {
                "id": 16000080,
                "name": "DRACO",
                "power": 9,
                "trophies": 4
              }
            }
          ],
          [
            {
              "tag": "#LV9QQLR08",
              "name": "nguyentran",
              "brawler": {
                "id": 16000005,
                "name": "SPIKE",
                "power": 11,
                "trophies": 4
              }
            },
            {
              "tag": "#LQQYGCV29",
              "name": "colin",
              "brawler": {
                "id": 16000050,
                "name": "GRIFF",
                "power": 10,
                "trophies": 3
              }
            },
            {
              "tag": "#2YQLQYL0L2",
              "name": "luviapro",
              "brawler": {
                "id": 16000027,
                "name": "8-BIT",
                "power": 11,
                "trophies": 4
              }
            }
          ]
        ]
      }
    },
    {
      "battleTime": "20250210T040619.000Z",
      "event": {
        "id": 15000115,
        "mode": "gemGrab",
        "map": "Double Swoosh"
      },
      "battle": {
        "mode": "gemGrab",
        "type": "soloRanked",
        "result": "defeat",
        "duration": 118,
        "starPlayer": {
          "tag": "#22QYVUY89",
          "name": "saahilggamer",
          "brawler": {
            "id": 16000009,
            "name": "DYNAMIKE",
            "power": 11,
            "trophies": 3
          }
        },
        "teams": [
          [
            {
              "tag": "#2P0YGRL82",
              "name": "M\u0105tt",
              "brawler": {
                "id": 16000026,
                "name": "BIBI",
                "power": 11,
                "trophies": 4
              }
            },
            {
              "tag": "#LV9QQLR08",
              "name": "nguyentran",
              "brawler": {
                "id": 16000034,
                "name": "JACKY",
                "power": 11,
                "trophies": 4
              }
            },
            {
              "tag": "#LQQYGCV29",
              "name": "colin",
              "brawler": {
                "id": 16000005,
                "name": "SPIKE",
                "power": 11,
                "trophies": 3
              }
            }
          ],
          [
            {
              "tag": "#22QYVUY89",
              "name": "saahilggamer",
              "brawler": {
                "id": 16000009,
                "name": "DYNAMIKE",
                "power": 11,
                "trophies": 3
              }
            },
            {
              "tag": "#PCY0VQYCV",
              "name": "Brawler",
              "brawler": {
                "id": 16000028,
                "name": "SANDY",
                "power": 11,
                "trophies": 4
              }
            },
            {
              "tag": "#22GYVJYYR",
              "name": "saazggamer",
              "brawler": {
                "id": 16000023,
                "name": "LEON",
                "power": 11,
                "trophies": 3
              }
            }
          ]
        ]
      }
    },
    {
      "battleTime": "20250210T040318.000Z",
      "event": {
        "id": 15000022,
        "mode": "bounty",
        "map": "Hideout"
      },
      "battle": {
        "mode": "bounty",
        "type": "soloRanked",
        "result": "victory",
        "duration": 85,
        "starPlayer": {
          "tag": "#LV9QQLR08",
          "name": "nguyentran",
          "brawler": {
            "id": 16000005,
            "name": "SPIKE",
            "power": 11,
            "trophies": 3
          }
        },
        "teams": [
          [
            {
              "tag": "#LV9QQLR08",
              "name": "nguyentran",
              "brawler": {
                "id": 16000005,
                "name": "SPIKE",
                "power": 11,
                "trophies": 3
              }
            },
            {
              "tag": "#LQQYGCV29",
              "name": "colin",
              "brawler": {
                "id": 16000003,
                "name": "BROCK",
                "power": 9,
                "trophies": 3
              }
            },
            {
              "tag": "#PVVLPULCG",
              "name": "make out hill",
              "brawler": {
                "id": 16000046,
                "name": "BELLE",
                "power": 9,
                "trophies": 3
              }
            }
          ],
          [
            {
              "tag": "#8C9PV2J2G",
              "name": "BS|\u2614\u1d0b\u026a\u029f\u029f\u1d07\u0280 \u1dab\u1d52\u1d5b\u1d49",
              "brawler": {
                "id": 16000070,
                "name": "CORDELIUS",
                "power": 10,
                "trophies": 337
              }
            },
            {
              "tag": "#8CP2YRJ9U",
              "name": "Super Star",
              "brawler": {
                "id": 16000043,
                "name": "EDGAR",
                "power": 8,
                "trophies": 352
              }
            },
            {
              "tag": "#8CPYQRVYP",
              "name": "leonardo_blt",
              "brawler": {
                "id": 16000079,
                "name": "ANGELO",
                "power": 9,
                "trophies": 344
              }
            }
          ]
        ]
      }
    },
    {
      "battleTime": "20250209T222135.000Z",
      "event": {
        "id": 0,
        "map": null
      },
      "battle": {
        "mode": "knockout",
        "type": "ranked",
        "result": "defeat",
        "duration": 64,
        "starPlayer": {
          "tag": "#PYUYLP29C",
          "name": "adalberto",
          "brawler": {
            "id": 16000001,
            "name": "COLT",
            "power": 11,
            "trophies": 566
          }
        },
        "teams": [
          [
            {
              "tag": "#LV9QQLR08",
              "name": "nguyentran",
              "brawler": {
                "id": 16000043,
                "name": "EDGAR",
                "power": 11,
                "trophies": 585
              }
            },
            {
              "tag": "#P2UGJYQ0R",
              "name": "ALTAG0G0\ud83d\udef8\ud83e\udd77\ud83c\udfff",
              "brawler": {
                "id": 16000001,
                "name": "COLT",
                "power": 11,
                "trophies": 579
              }
            },
            {
              "tag": "#28YVVY0C8U",
              "name": "pupuce",
              "brawler": {
                "id": 16000014,
                "name": "BO",
                "power": 9,
                "trophies": 372
              }
            }
          ],
          [
            {
              "tag": "#PYUYLP29C",
              "name": "adalberto",
              "brawler": {
                "id": 16000001,
                "name": "COLT",
                "power": 11,
                "trophies": 566
              }
            },
            {
              "tag": "#2Q0CQQJC2Q",
              "name": "zafiro 2.0",
              "brawler": {
                "id": 16000049,
                "name": "BUZZ",
                "power": 11,
                "trophies": 570
              }
            },
            {
              "tag": "#8U28Y98L",
              "name": "Chamuco \ud83d\udc7a\ud83c\uddf2\ud83c\uddfd",
              "brawler": {
                "id": 16000040,
                "name": "AMBER",
                "power": 9,
                "trophies": 597
              }
            }
          ]
        ]
      }
    },
    {
      "battleTime": "20250209T222005.000Z",
      "event": {
        "id": 0,
        "map": null
      },
      "battle": {
        "mode": "knockout",
        "type": "ranked",
        "result": "victory",
        "duration": 101,
        "starPlayer": {
          "tag": "#G8L9Q0PQQ",
          "name": "deni<3",
          "brawler": {
            "id": 16000001,
            "name": "COLT",
            "power": 11,
            "trophies": 590
          }
        },
        "teams": [
          [
            {
              "tag": "#220G9VUP",
              "name": "steeven",
              "brawler": {
                "id": 16000017,
                "name": "TARA",
                "power": 9,
                "trophies": 598
              }
            },
            {
              "tag": "#QP89JYGJJ",
              "name": "NAUGHTYJAMIN 00",
              "brawler": {
                "id": 16000045,
                "name": "STU",
                "power": 11,
                "trophies": 594
              }
            },
            {
              "tag": "#LV9QQLR08",
              "name": "nguyentran",
              "brawler": {
                "id": 16000043,
                "name": "EDGAR",
                "power": 11,
                "trophies": 585
              }
            }
          ],
          [
            {
              "tag": "#G8L9Q0PQQ",
              "name": "deni<3",
              "brawler": {
                "id": 16000001,
                "name": "COLT",
                "power": 11,
                "trophies": 590
              }
            },
            {
              "tag": "#2LGPQLQVJG",
              "name": "big_mac",
              "brawler": {
                "id": 16000009,
                "name": "DYNAMIKE",
                "power": 10,
                "trophies": 598
              }
            },
            {
              "tag": "#RR9CLC22U",
              "name": "JESSIE",
              "brawler": {
                "id": 16000023,
                "name": "LEON",
                "power": 9,
                "trophies": 597
              }
            }
          ]
        ]
      }
    },
    {
      "battleTime": "20250209T221747.000Z",
      "event": {
        "id": 0,
        "map": null
      },
      "battle": {
        "mode": "knockout",
        "type": "ranked",
        "result": "victory",
        "duration": 111,
        "starPlayer": {
          "tag": "#LV9QQLR08",
          "name": "nguyentran",
          "brawler": {
            "id": 16000043,
            "name": "EDGAR",
            "power": 11,
            "trophies": 585
          }
        },
        "teams": [
          [
            {
              "tag": "#2GVJ0JQPLV",
              "name": "chiki pro",
              "brawler": {
                "id": 16000018,
                "name": "DARRYL",
                "power": 9,
                "trophies": 553
              }
            },
            {
              "tag": "#LV9QQLR08",
              "name": "nguyentran",
              "brawler": {
                "id": 16000043,
                "name": "EDGAR",
                "power": 11,
                "trophies": 585
              }
            },
            {
              "tag": "#2L22RC90JR",
              "name": "\ud83d\udd77\ufe0f",
              "brawler": {
                "id": 16000015,
                "name": "PIPER",
                "power": 9,
                "trophies": 576
              }
            }
          ],
          [
            {
              "tag": "#GQVL2QQC",
              "name": "ShadowLion",
              "brawler": {
                "id": 16000056,
                "name": "EVE",
                "power": 9,
                "trophies": 585
              }
            },
            {
              "tag": "#890Y0G992",
              "name": "void_reaver",
              "brawler": {
                "id": 16000004,
                "name": "RICO",
                "power": 9,
                "trophies": 599
              }
            },
            {
              "tag": "#2GC888LQGL",
              "name": "cristo77p",
              "brawler": {
                "id": 16000009,
                "name": "DYNAMIKE",
                "power": 11,
                "trophies": 597
              }
            }
          ]
        ]
      }
    },
    {
      "battleTime": "20250209T221507.000Z",
      "event": {
        "id": 0,
        "map": null
      },
      "battle": {
        "mode": "knockout",
        "type": "ranked",
        "result": "defeat",
        "duration": 104,
        "starPlayer": {
          "tag": "#PQ8YPLYPL",
          "name": "i cuddle with",
          "brawler": {
            "id": 16000047,
            "name": "SQUEAK",
            "power": 11,
            "trophies": 472
          }
        },
        "teams": [
          [
            {
              "tag": "#LV9QQLR08",
              "name": "nguyentran",
              "brawler": {
                "id": 16000005,
                "name": "SPIKE",
                "power": 11,
                "trophies": 497
              }
            },
            {
              "tag": "#2LQGR08RL9",
              "name": "GOJO EL INSANO\u2623",
              "brawler": {
                "id": 16000000,
                "name": "SHELLY",
                "power": 9,
                "trophies": 483
              }
            },
            {
              "tag": "#2Q0YRRQJUU",
              "name": "bot1",
              "brawler": {
                "id": 16000068,
                "name": "MAISIE",
                "power": 8,
                "trophies": 503
              }
            }
          ],
          [
            {
              "tag": "#PQ8YPLYPL",
              "name": "i cuddle with",
              "brawler": {
                "id": 16000047,
                "name": "SQUEAK",
                "power": 11,
                "trophies": 472
              }
            },
            {
              "tag": "#9UQJ0YCRQ",
              "name": "j\u201do\u201d",
              "brawler": {
                "id": 16000012,
                "name": "CROW",
                "power": 11,
                "trophies": 479
              }
            },
            {
              "tag": "#PUG2YUG82",
              "name": "hey there pal",
              "brawler": {
                "id": 16000049,
                "name": "BUZZ",
                "power": 11,
                "trophies": 465
              }
            }
          ]
        ]
      }
    }
  ],
  "paging": {
    "cursors": {}
  }
}